[ {
  "url" : "http://thiendia.com/diendan/threads/ben-juk-no-2.1108189/",
  "title" : "Ben Juk No.2",
  "unixTime" : 1501850498,
  "imgUrls" : [ "https://s2.postimg.org/9ap1i45x5/VID_20170209_6713_000010_20170209-114857.jpg", "https://s2.postimg.org/3l8sxszqx/VID_20170209_6713_000006_20170209-114826.jpg", "https://s2.postimg.org/z3oweh43d/VID_20170209_6713_000005_20170209-114817.jpg" ],
  "intro" : ".. Chíp trắng"
}, {
  "url" : "http://thiendia.com/diendan/threads/can-tho-rau-ruot-9x-d.1108176/",
  "title" : "[Cần Thơ] Rau ruột 9x :D",
  "unixTime" : 1501846978,
  "imgUrls" : [ "http://server8.upload69.net/images/2017/08/04/P_20170312_200525af0f3.jpg", "http://server8.upload69.net/images/2017/08/04/P_20170312_20122274d64.jpg" ],
  "intro" : "Lần đầu ấy mặc, không biết mặc vậy đúng không ta"
}, {
  "url" : "http://thiendia.com/diendan/threads/thinh-cua-mot-tv-moi.1108171/",
  "title" : "Thính của một tv mới",
  "unixTime" : 1501845447,
  "imgUrls" : [ "http://server8.upload69.net/image/ZJ8PT", "http://server8.upload69.net/images/2017/08/04/IMG_045593a83.jpg", "http://server8.upload69.net/images/2017/08/04/IMG_0456f18bd.jpg", "http://server8.upload69.net/images/2017/08/04/IMG_0457c6901.jpg", "http://server8.upload69.net/images/2017/08/04/IMG_04589bc4e.jpg", "http://server8.upload69.net/images/2017/08/04/IMG_0459f2f72.jpg" ],
  "intro" : "Hi các anh chị, em tham gia dd cũng gần 02 tháng rùi, nay mới có dịp gửi lên ít hình selfie. Mong ac ghé qua và cho em ít lời để box vui hơn ạ.\n#AD: em người mới nên có gì xin các anh cứ nhắc nhở nếu có gì sai trái, đừng ban nha.\nhttp://server8.upload69.net/image/ZJ8PT\nhttp://server8.upload69.net/image/ZJEuH\nhttp://server8.upload69.net/image/ZJS56\nhttp://server8.upload69.net/image/ZJIxV\nhttp://server8.upload69.net/image/ZJe"
}, {
  "url" : "http://thiendia.com/diendan/threads/my-trinh-0647-gai-que-huong-dong-chat-nhu-nuoc-cat-chich-chich.1108168/",
  "title" : "TDH-NTĐ - PIC - 300K - MỸ TRINH 0647 - GÁI QUÊ HƯƠNG ĐỒNG - CHẤT NHƯ NƯỚC CẤT - CHỊCH CHỊCH",
  "unixTime" : 1501844601,
  "imgUrls" : [ "http://server8.upload69.net/images/2017/08/03/113b31.jpg", "http://server8.upload69.net/images/2017/08/03/273a8a.jpg", "http://server8.upload69.net/images/2017/08/03/312d31.jpg", "http://server8.upload69.net/images/2017/08/03/4e8b29.jpg", "http://server8.upload69.net/images/2017/08/03/519f85.jpg", "http://server8.upload69.net/images/2017/08/03/6269e8.jpg", "http://server8.upload69.net/images/2017/08/03/71d516.jpg", "http://server8.upload69.net/images/2017/08/03/8e8e4b.jpg", "http://server8.upload69.net/images/2017/08/03/907a0b.jpg", "http://server8.upload69.net/images/2017/08/03/100992e.jpg", "http://server8.upload69.net/images/2017/08/03/11ca5ca.jpg", "http://server8.upload69.net/images/2017/08/03/1250241.jpg", "http://server8.upload69.net/images/2017/08/03/13f01f9.jpg", "http://server8.upload69.net/images/2017/08/03/1478b9e.jpg", "http://server8.upload69.net/images/2017/08/03/155e855.jpg", "http://server8.upload69.net/images/2017/08/03/16549ca.jpg", "http://server8.upload69.net/images/2017/08/03/17a69dc.jpg" ],
  "intro" : "Lâu lắm rồi mới có 1 bé mà khiến tay chơi như tôi có 1 cảm nhận khác. em khá nhẹ nhàng, bẽn lẽn, Chưa biết gì nhiều, ngoài những động tác mơn trớn mà bất cứ người nào lớn cũng có kĩ năng đơn giản vậy. 1 cuộc khảo sát nhỏ và em được lên lịch để học hỏi thêm về những chiêu thức mới cũng như cách phục vụ anh em các bác sao cho thật tốt. giờ đã thành công và có thể xuống núi để phuc vụ anh em rồi đó.\n\n===== THÔNG TIN THAM KHẢO =====\nNghệ Danh: MỸ TRINH\nGiá : 300K/ 1 SHOT\nPass : Bạn anh thiendia\nKhu vực : TDH\nGiá KS/NN : 100K - 120K/2h\nThời gian hoạt động: 11h - 24h\nSĐT : 0168xxx0647\nMÔ TẢ VỀ NGƯỜI ĐẸP\nFace : Khuôn mặt sáng, xinh, dễ thương, còn nét mộc\nBody: em sở hữu làn da mịn màng, mát lạnh,\nNgực : ngực bánh dày đẹp tự nhiên, to vừa bóp đã tay, anh em thoải mái mà nhào nặn nhé.\nEo : mình dây,eo thon,rất đẹp\nMông : Mông mịn màng, cong cớn, doggy sướng thôi rồi\nBướm : lông lá tỉa tót gọn gàng, thơm tho sạch sẽ, nước nôi chan chứa, bướm khá khít chơi phê\n\nDỊCH VỤ CAM KẾT\nSV : Chiều khách hết max là điểm mạnh của em nó HJ, BJ, WC mút đầu gối. đá cà, múa cột bài bản tình cảm, phang phập thoái mái không hối thúc, ngoan ngoãn đổi các tư thế rất hợp tác trong lúc chiến đấu, bác nào thích các dòng hàng tình cảm kèm body rực lửa , kinh nghiệm làm tình đỉnh cao thì em nó là một sự lựa chọn tuyệt vời, nói chung em nó rất dâm nhé đi chơi hiếm có gặp mấy em hàng ngon và dâm dzữ như zậy.\nCam kết : Hôn môi + Vét + Hj, Bi, Hôn ti - Liếm Cà - Múa Cột + Tắm chung\n- Hôn vú, Bóp vú, mút mát Ti : Có\n- HJ + BJ : Có\n- Vét : Có\n- Hợp tác mọi tư thế có cả 69 - 96\nKhông Cam Kết : CIA, Lỗ Nhị\nQua đêm : Ko\nKẾT LUẬN: lần đầu tiên em nó lên sóng, đã được chỉ bảo 1 số kĩ năng cơ bản. rất chịu khó nghe lời và làm theo những gì a e muốn. Phân khúc 300k dự là em nó sẽ rất hút đấy ạ.\n\nCAM KẾT\n- KHÔNG ẢNH ẢO - KHÔNG CÔNG NGHIỆP - KHÔNG BOM KHÁCH - KHÔNG TRÁO HÀNG\n\nCHÚ Ý\n– Đọc kỹ thông tin trước khi check.\n– Thể hiện văn hóa checker lịch sự khi check hàng.\n+ Khi check hàng không: sử dụng ma túy, thuốc kích dục, quá say xỉn, dọa nạt, bạo dâm hoặc có những đòi hỏi quá đáng đối với em.\n+ Em được phép từ chối phục vụ các bác quá già (trên 60 tuổi), được phép từ chối các anh đã tân trang súng ống bằng cách lắp thêm phụ kiện.\n– Các checker khi check về nhớ có report, phản ánh.\n– AE Checker lưu ý : Lịch sự, vệ sinh sạch sẽ để được phục vụ như mong muốn.\nChúc các checker có những phút giây thăng hoa bên cạnh người đẹp !!!​"
}, {
  "url" : "http://thiendia.com/diendan/threads/gai-goi-huong-ly-2909-hang-moi-massa-liem-lap-toan-than-ngoan-tinh-cam.1108167/",
  "title" : "TDH-NTĐ - Ngon - PIC - 400K - Gái Gọi Hương Ly 2909 - Hàng Mới Massa Liếm Láp Toàn Thân , Ngoan , Tình Cảm",
  "unixTime" : 1501844542,
  "imgUrls" : [ "http://imageshack.com/a/img923/1338/XzRglq.jpg", "http://server8.upload69.net/images/2017/08/04/44bfb2.md.jpg", "http://server8.upload69.net/images/2017/08/04/243f38.md.jpg", "http://server8.upload69.net/images/2017/08/04/390177.md.jpg", "http://server8.upload69.net/images/2017/08/04/7fb82d.md.jpg", "http://server8.upload69.net/images/2017/08/04/67961d.md.jpg", "http://server8.upload69.net/images/2017/08/04/87d8bf.md.jpg" ],
  "intro" : "Chào anh em\nHà Nội vào đợt mưa dai dẳng , được nằm cạnh em tâm sự chuyện vui buồn vừa vuốt ve nhau tâm sự chuyện trên trời dưới đất , nghe những bản nhạc nhẹ nhàng,sâu lắng dưới cơn mưa của Trung Quân idol , rồi hòa quyện vào nhau thì còn gì bằng .\n\nDo quen em từ trước ( cùng quê ) gặp được nhau trên HN cũng là cái duyên , dòng đời đưa đẩy , gia đình khó khăn em nó phải rời quê hương lên HN kiếm tiền nuôi gia đình\n\nem người nhỏ nhắn dáng dây ,( 1m65) nước da hơi ngăm khỏe khoắn đặc trưng của em gái thôn quê . e rất tình cảm nhé , mong các bác đừng dọa em ý . ấn tượng của tôi về em nó là rất ngoan và chiều.\nDo trời mưa bẩn mình vào tắm rửa chút , em cũng tự động theo vào tắm rửa kỳ cọ chim cò cho mình ^^ , tắm mát mẻ xong 2 ae nằm ra giường , em liếm láp từ đầu đến chân , BJ liếm ti đá bi rất nhiệt tình , mình bảo thôi mới thôi . Rồi 2 thần thể ướt át hòa vào nhau trong tiếng mưa và điệu nhạc nhẹ đầy tình cảm ^^ , tiếng pạch pạch quen thuộc , sự tê dại của tình dục , xóa tan đi căng thẳng mệt mỏi sau tuần làm việc mệt mỏi và những chuyện đau đầu vây quanh .\n\nDo em là mới làm , các ae check nhớ giữ gìn để ae khác còn có cái dùng chung nhé , Anh em nào muốn số thì cứ ĐẶT GẠCH TẠI TOPIC và ĐỪNG INBOX ( Mình sẽ tự share số qua inbox cho các bác )\nTHÔNG TIN\nGái Gọi: Hương Ly\nMã số: 2909\nTuổi : U96\n\nSố điện thoại:\n016*****909\n\nPass: lấy số thiendia\n\nLoại Hàng: Gái gọi Hà Nội\n\nGiá: 400k/1shot , qua đêm 1tr2\n\nGiá NN: 100k – 120k/2h đầu\n\nKhu vực: Trần Duy Hưng\n\nThời gian: 40 phút trở lên\n\nTime làm việc: cả ngày\n\nĐÁNH GIÁ CƠ BẢN\nFace : Mặt ưa nhìn , da mịn màng ngăm khỏe . Dáng cao\n\nNgực : bé nhưng vừa tay , bú mút liếm láp thoải mái\n\nEo : Đẹp không tì vết\n\nMông : Vừa , cong vút , chổng lên đầy gợi dục\n\nBym : khít , nước lôi nhiều , lông lá tự nhiên, rất sạch sẽ , tevet ngon . không mùi​\n\nDịch Vụ Cam Kết :\n+ Hôn môi, đá lưỡi : Có các kiểu con đà điểu luôn.\n+ Bj : Có ( Bj nhiệt tình bảo thôi mới thôi )\n+ Hj : không\n+ Tevet ( vét máng ) : Có\n+ Xuất tinh alo ( xuất tinh miệng ) : ko\n+ 69-96: Có\n+ La liếm toàn thân: Có ( Em nó la liếm, mút ngón chân, liếm bẹn, mút cà, liếm ngực, …… cứ nằm im em nó phục vụ , các bác chỉ việc rên\n+ Chơi lỗ nhị ( thông đít ) : Không\n+ Thời gian phục vụ : Từ 40p đến 45p. khách cứ thỏa mái e nó ko giục. công nghiệp .\nCác dịch vụ khác : các bác tự thỏa thuận với em ý nhé\nThái Độ : Tình cảm , Ngoan ngoãn , nhẹ nhàng ,ngại ngùng như gái mới lớn , chiều khách . Hợp tác mọi tư thế chiến đấu chỉ cần các bác nhẹ nhàng lịch sự , Phục vụ nhiệt tình , đem lại cảm giác thoả mái nhất cho anh em khi đi check .\nsau đây có ít ảnh cho anh em thị dâm:"
}, {
  "url" : "http://thiendia.com/diendan/threads/mbtm-tuyet-6760-mua-lanh-gap-em-am-ca-nguoi.1108160/",
  "title" : "Ngon - Tân Bình - PIC - 200K - MBTM TUYẾT 6760 - Mưa Lạnh Gặp Em Ấm Cả Người",
  "unixTime" : 1501841904,
  "imgUrls" : [ "http://server8.upload69.net/images/2017/08/04/z732451525403_23c59d7f189bc9f40257d14ba7fd1d77b638a.jpg", "http://server8.upload69.net/images/2017/08/04/z732451553414_f6fb8b0941649d48e34780128015bd21fc9b7.jpg", "http://server8.upload69.net/images/2017/08/04/z732451659073_feca6734e78cfbb642245f87dafaa2990dd94.jpg", "http://server8.upload69.net/images/2017/08/04/z732451727387_fc4d5fdb2f86e2793a036768cbeab22ed420e.jpg", "http://server8.upload69.net/images/2017/08/04/z732451790838_7cc8c19592ba9b8e224e599e34d98c0f86aa0.jpg", "http://server8.upload69.net/images/2017/08/04/z732451846174_12e527cdf739d5cf1e83f3012f028212f4d6c.jpg" ],
  "intro" : "Mưa lạnh lẽo buồn bã bỗng dưng thèm cảm giác ôm ấp, làm tình này kia kia nọ nên lại gọi cho MB Tuyết để xã lũ vì cũng gần nhà mà giá lại rẽ. Em này theo mình là khá ngon trong thời bão giá và lạm phát trong thời buổi hiện nay\n\nĐánh giá U như kỹ nha các đồng dâm\n\nFace: theo mình là tạm ổn ko đến nổi cá sấu, rất có duyên\nV1: bự còn săn chắc bóp rất đã, sướng nhất là khi BJ 2 trái bưởi của em ấy cứ cạ cạ vô đùi làm phê lắm\nV2: hơi tròn MB mà được cái săn chắc chưa chảy xệ\nV3: mông trắng to bự doggy kích thích lắm\nV4: sạch sẽ, lúc hứng quá vét luôn rất đã\nPhục Vụ: làm tình bài bản có nghề, rên la rất quằn quại nghe mà cũng ngại nhưng sướng vì em dâm quá, nói chuyện cũng vui vẻ nói chung giá vậy quá tốt cho một lần xuất tinh thoải mái tâm hồn\n\nGiá 200K/s quá xá rẽ khu vực Tân Bình\n\nMáy bay này mình lấy thông tin tại đây\nhttp://thiendia.com/diendan/threads...ong-nay-bay-thoai-mai-khong-lo-ve-gia.963126/\n\nmột vài hình ảnh chụp được"
}, {
  "url" : "http://thiendia.com/diendan/threads/lau-roi-moi-dang-anh-vk.1108158/",
  "title" : "Lâu rồi mới đang ảnh vk",
  "unixTime" : 1501840762,
  "imgUrls" : [ "http://server8.upload69.net/images/2017/08/04/imagef63d1.jpg", "http://server8.upload69.net/images/2017/08/04/image9c69f.jpg", "http://server8.upload69.net/images/2017/08/04/image4b853.jpg", "http://server8.upload69.net/images/2017/08/04/image459a6.jpg", "http://server8.upload69.net/images/2017/08/04/image19da3.jpg", "http://server8.upload69.net/images/2017/08/04/image2d67b.jpg", "http://server8.upload69.net/images/2017/08/04/image89e62.jpg", "http://server8.upload69.net/images/2017/08/04/image8d6ec.jpg", "http://server8.upload69.net/images/2017/08/04/image304d4.jpg" ],
  "intro" : "Đây là chụp trước khi chịch của vk ck mình. Văn không hay chữ thì không tốt, đã học rốt lại còn k có nhiều tiền lên chẳng biết viết gì cả chỉ để đây và chúc các đồng dâm ngon miệng nhé. Các đồng dâm cứ bình luận nhiệt tình về quả bướm và quả mông của vk mình đê mình cho vk mình đọc nhé. Cảm ơn các đồng dâm"
}, {
  "url" : "http://thiendia.com/diendan/threads/phi-cong-nhay-du-u38-kv-tay-ho.1108157/",
  "title" : "Phi công nhẩy dù u38 KV tây hồ",
  "unixTime" : 1501840171,
  "imgUrls" : [ "http://sv1.upsieutoc.com/2017/08/04/IMG_0007.jpg" ],
  "intro" : "Chào AE lâu rồi không chia sẻ\n\nChuyện là thế này Mình có lang thang trên zalo và vớ được quả MB này . không biết có đụng với đồng dâm nào không nếu MB đã có trên này thì sorry nhé\nBắt đầu làm quen với MB chat chit rất lịch sự\nthỉnh thoảng mơn trớn tí nói đùa tí thế éo nào mà 1 nốt đã choén rồi\nChả là Ck MB đã bỏ cách đây 7 năm theo như tâm sự thì cũng it choén cho nên bím rất ngon lông thì lưa thưa\nChả nói dài làm gì vào vấn đề nào:\nF: 3đ hơi giừ\nV1: 5 +1 điểm : vú bánh dầy không chẩy không nhão thêm 1 điểm vì vẫn có sữa phê lòi kkkk\nV2: 3 MB ko tránh được mỡ\nV3 :9d To căng như 2 cái lồng bàn đã luôn doggy tẹt\nSevice :BJ nhiệt tình\nNước rất nhiều\nShare cho đối tượng như sau : 8x trở lên . lịch sự bảo đảm không đâm dao sau lưng\ncomment hoặc Inbox sdt tôi sẽ trọn 1 người duy nhất\nthank ae đọc bài . share thật không nói chơi"
}, {
  "url" : "http://thiendia.com/diendan/threads/gai-goi-nha-trang-hoang-yen-6259-chuan-muc-cua-su-tan-tam.1108151/",
  "title" : "[Đã Kiểm Định] - 400K - gái gọi Nha Trang: Hoàng Yến 6259 - Chuẩn mực của sự tân tâm",
  "unixTime" : 1501838051,
  "imgUrls" : [ "http://server1.postpixx.com/images/2017/06/28/cf76ed3d0ccbaa44c769d1a3fbfa0aca.jpg", "http://server1.postpixx.com/images/2017/06/28/z699814141891_11d1510c8a4ea58e17d379565a84fe53.jpg", "http://server1.postpixx.com/images/2017/06/28/z699814182192_c4b0513c1b36b55b756cf142e914e7ef.jpg", "http://server1.postpixx.com/images/2017/06/28/z699814202319_b8546fa2cd084685424bbb96c605c272.jpg", "http://server1.postpixx.com/images/2017/06/28/z699814238813_fce899584b16fde0ede2783e5849ca26.jpg", "http://server1.postpixx.com/images/2017/06/28/z699814284845_cd2f2002ab3c122402a5fec8ac8873d8.jpg", "http://server1.postpixx.com/images/2017/06/28/z699814301152_dd59fe0a82e8335d4f0a3f37a85de1a0.jpg", "http://server1.postpixx.com/images/2017/06/28/z699814322659_67c485a4b5f89dcdbea5880481580fd7.jpg", "http://server1.postpixx.com/images/2017/06/28/z699814353782_5a14273b2cf9be9e933c4db1ca1b616c.jpg", "http://server7.upload69.net/images/2016/12/11/1481430564112_14929912.jpg", "http://server7.upload69.net/images/2016/12/11/1481430564162_150f291b.jpg", "http://server7.upload69.net/images/2016/12/11/1481430564198_15168f3f.jpg", "http://server7.upload69.net/images/2016/12/11/1481430564278_153a5544.jpg", "http://server7.upload69.net/images/2016/12/11/1481430564320_154c801e.jpg", "http://server7.upload69.net/images/2016/12/11/1481430564348_1550f30c.jpg", "http://server7.upload69.net/images/2016/12/11/1481430564398_156ed7d5.jpg", "http://server7.upload69.net/images/2016/12/11/1481430564432_1579d46e.jpg", "http://server7.upload69.net/images/2016/12/11/1481430564595_159a596b.jpg", "http://server7.upload69.net/images/2016/12/11/1481430564653_160b1b76.jpg", "http://server7.upload69.net/images/2016/12/11/1481430564695_161dcade.jpg", "http://server7.upload69.net/images/2016/12/11/1481430564745_16247562.jpg" ],
  "intro" : "gái gọi Hoàng Yến​\nLoại hàng: gái gọi Nha Trang​\nNăm sinh : 1991\nNguyên Quán : Miền Bắc\nNguồn hàng : Từ Đà Nẵng​\nMã số: 6259​\nGiá: 400k/ Shot\n\nThời gian phục vụ cam kết : 40p​\nKhu vực hoạt động: TP Nha Trang​\nGiá nhà nghỉ : 100k/2h đầu​\nThời gian hoạt động :10h-22h​\n​\nSố điện thoại gái gọi: 0938 26 6259​\nPass: Lấy số trên thiendia.com​\n​LINK REPORT THAM KHẢO VỀ GÁI GỌI NÀY\nhttp://thiendia.com/diendan/threads/gai-goi-da-nang-hoang-yen-8259-chuan-muc-cua-su-tan-tam.1056758/\n\nTHÔNG TIN THAM KHẢO :\n\nNhận xét tổng thể:\n\nFace : Mộc mạc chân chất rất ưa nhìn\nBody : Săn chắc khoẻ khoắn\nV1 : To tròn, bú bóp tẹt ga\nV2 : Có chút mỡ nhưng ổn\nV3 : Tròn lẳng , rất chắc doggy quá ngon\nV4 : Bím múp, lông lá gọn gàng và sạch sẽ\n\nCác dịch vụ:\nBj, Hj: Có\nHôn môi: Có (Vệ sinh răng miệng sạch sẽ, không say xỉn)\nTevez: Có\nHôn ngực: Có\nTắm cho khách: Có\nMassage, tâm sự: Nếu có thời gian\nSome: Không\nLỗ nhị: Không\nChống chỉ định: Say xỉn quá độ, bẩn bựa, bạo dâm, gắn bi gắn kiếm\n\nHÌNH ẢNH :"
}, {
  "url" : "http://thiendia.com/diendan/threads/gai-goi-hoang-yen-6259-chuan-muc-cua-su-tan-tam.1108151/",
  "title" : "[Đã Kiểm Định] - 400K - gái gọi Hoàng Yến 6259 - Chuẩn mực của sự tân tâm",
  "unixTime" : 1501838051,
  "imgUrls" : [ "http://server1.postpixx.com/images/2017/06/28/cf76ed3d0ccbaa44c769d1a3fbfa0aca.jpg", "http://server1.postpixx.com/images/2017/06/28/z699814141891_11d1510c8a4ea58e17d379565a84fe53.jpg", "http://server1.postpixx.com/images/2017/06/28/z699814182192_c4b0513c1b36b55b756cf142e914e7ef.jpg", "http://server1.postpixx.com/images/2017/06/28/z699814202319_b8546fa2cd084685424bbb96c605c272.jpg", "http://server1.postpixx.com/images/2017/06/28/z699814238813_fce899584b16fde0ede2783e5849ca26.jpg", "http://server1.postpixx.com/images/2017/06/28/z699814284845_cd2f2002ab3c122402a5fec8ac8873d8.jpg", "http://server1.postpixx.com/images/2017/06/28/z699814301152_dd59fe0a82e8335d4f0a3f37a85de1a0.jpg", "http://server1.postpixx.com/images/2017/06/28/z699814322659_67c485a4b5f89dcdbea5880481580fd7.jpg", "http://server1.postpixx.com/images/2017/06/28/z699814353782_5a14273b2cf9be9e933c4db1ca1b616c.jpg", "http://server7.upload69.net/images/2016/12/11/1481430564112_14929912.jpg", "http://server7.upload69.net/images/2016/12/11/1481430564162_150f291b.jpg", "http://server7.upload69.net/images/2016/12/11/1481430564198_15168f3f.jpg", "http://server7.upload69.net/images/2016/12/11/1481430564278_153a5544.jpg", "http://server7.upload69.net/images/2016/12/11/1481430564320_154c801e.jpg", "http://server7.upload69.net/images/2016/12/11/1481430564348_1550f30c.jpg", "http://server7.upload69.net/images/2016/12/11/1481430564398_156ed7d5.jpg", "http://server7.upload69.net/images/2016/12/11/1481430564432_1579d46e.jpg", "http://server7.upload69.net/images/2016/12/11/1481430564595_159a596b.jpg", "http://server7.upload69.net/images/2016/12/11/1481430564653_160b1b76.jpg", "http://server7.upload69.net/images/2016/12/11/1481430564695_161dcade.jpg", "http://server7.upload69.net/images/2016/12/11/1481430564745_16247562.jpg" ],
  "intro" : "gái gọi Hoàng Yến​\nLoại hàng: gái gọi Nha Trang​\nNăm sinh : 1991\nNguyên Quán : Miền Bắc\nNguồn hàng : Từ Đà Nẵng​\nMã số: 6259​\nGiá: 400k/ Shot\n\nThời gian phục vụ cam kết : 40p​\nKhu vực hoạt động: TP Nha Trang​\nGiá nhà nghỉ : 100k/2h đầu​\nThời gian hoạt động :10h-22h​\n​\nSố điện thoại gái gọi: 0938 26 6259​\nPass: Lấy số trên thiendia.com​\n​LINK REPORT THAM KHẢO VỀ GÁI GỌI NÀY\nhttp://thiendia.com/diendan/threads/gai-goi-da-nang-hoang-yen-8259-chuan-muc-cua-su-tan-tam.1056758/\n\nTHÔNG TIN THAM KHẢO :\n\nNhận xét tổng thể:\n\nFace : Mộc mạc chân chất rất ưa nhìn\nBody : Săn chắc khoẻ khoắn\nV1 : To tròn, bú bóp tẹt ga\nV2 : Có chút mỡ nhưng ổn\nV3 : Tròn lẳng , rất chắc doggy quá ngon\nV4 : Bím múp, lông lá gọn gàng và sạch sẽ\n\nCác dịch vụ:\nBj, Hj: Có\nHôn môi: Có (Vệ sinh răng miệng sạch sẽ, không say xỉn)\nTevez: Có\nHôn ngực: Có\nTắm cho khách: Có\nMassage, tâm sự: Nếu có thời gian\nSome: Không\nLỗ nhị: Không\nChống chỉ định: Say xỉn quá độ, bẩn bựa, bạo dâm, gắn bi gắn kiếm\n\nHÌNH ẢNH :"
} ]