[ {
  "url" : "http://thiendia.com/diendan/threads/gai-goi-trung-son-kieu-oanh-ms-7721-co-em-kinh-can-chua-tung-buoc-vao-nghe.1089914/",
  "title" : "Trung Sơn-Q.8 - PIC - 400K - gái gọi trung sơn - Kiều Oanh - ms : 7721 - cô em kính cận chưa từng bước vào nghề",
  "unixTime" : 1496872800,
  "imgUrls" : [ "https://s18.postimg.org/dqu1o6up5/20170507_153025.jpg", "https://s18.postimg.org/7eewecrmx/20170507_153031.jpg", "https://s18.postimg.org/8uqewhujt/20170507_153053.jpg", "https://s18.postimg.org/h1n01ta09/20170507_153113.jpg", "https://s18.postimg.org/4oa5uwkbt/20170507_153218.jpg", "https://s18.postimg.org/bsrz3xrl5/20170507_153314.jpg", "https://s18.postimg.org/lrcxqf10p/20170507_153341.jpg", "https://s18.postimg.org/6jwy62961/20170507_153444.jpg", "https://s18.postimg.org/n8ye1z5rd/20170507_153611.jpg", "https://s18.postimg.org/v2yznddk9/20170507_153713.jpg", "https://s18.postimg.org/et8tkh2w9/20170507_153807.jpg", "https://s18.postimg.org/iqw39vppl/20170507_153845.jpg", "https://s18.postimg.org/ogcbu6vvt/20170507_154016.jpg", "https://s18.postimg.org/bqcouudbd/20170507_154156.jpg", "https://s18.postimg.org/dw6zpcgrt/z654523184072_77b975048cc98a95efad64b6194cf6b6.jpg", "https://s18.postimg.org/405wppazt/z654523197176_bd6fd577ae5a84dc6d466b7b2babb029.jpg", "https://s18.postimg.org/41fuj4ctl/z654523205925_def61d577db0e86127dc8c178c5fc133.jpg", "https://s18.postimg.org/xumurq1gp/z654523206362_382362588348404ff029cdebf86bb6ea.jpg", "https://s18.postimg.org/n92zfpv55/z654523211243_e2a28e06ff75848b8a6f5ec1801fa5b0.jpg", "https://s18.postimg.org/nn4bfbf8p/z654523215410_dad7299c5c006d441678f32fa14f7431.jpg" ],
  "intro" : "hôm kia chịch 1 em kính cận , giới thiệu anh em xong được 2 ngày thì em goi điện\n- anh ơi giúp bạn em với anh ơi .\ncái số đúng hưởng , nhận lời ngay\nđến lấy phòng nhắn cho cô chị 10 phút sau cô em gõ cửa .\nui chà lại kính cận , chị em nhà này cận cả à ?\nmà phải công nhận thời buổi này nhà nào mà nhiều con gái kiểu gì cũng lấy lỗ làm lãi he he.\n\nem này lại còn chưa đi làm bao giờ , bố khỉ thế là phải vác cái thân già ngồi hướng dẫn rồi ác cái xác ra để em thục tập tốt nghiệp nhanh .\n\nphải công nhận em học miệt mài , em học cũng khá và giỏi nên thằng con chêt lên chết xuống , nguyên chiều ủn luôn 2 nháy rồi về nhà ngất lâm sàng , giờ mới online bum lên đây cho anh em .\n\nThông tin :\n\nNghệ danh : Gái gọi Kiều oanh\nMã số : 7721\nNăm sinh : 1993\nLoại hàng : Gái gọi sài gòn\nXuất xứ : miền Bắc\nKhu vực hoạt động : Trung sơn - quận 8\nGiá : 400k / 1 shot - có đi theo tiếng - có qua đêm ( anh em tự liên hệ )\nGiá khách sạn : 80k - 120k tùy loại phòng\nthời gian phục vụ : trung bình 40 phút 1 shot\nthời gian làm việc : sáng 10h sáng đến 23h đêm ( sau đó nhận qua đêm )\n\nĐánh giá nhanh mang tính chủ quan\n\nCao: 1m63\nNặng : Khoảng 50 kg\nMặt : xinh , nhìn trí thức , miệng xinh , kính cận , mũi cao , cười duyên .\nLàn da : Trắng trung bình , mịn màng\nBody : vừa vặn , không thừa không tiếu , không gầy không beo.\nVòng 1 : hệ bưởi , hàng sịn 100% , bóp bú bét nhè .\nVòng 2 : tròn xinh , không bèo nhèo .\nVòng 3 : Mông tròn & lán mịn .\nVòng 4: Còn đẹp, không cavat .\nService : mới học , bj , hj , bú liếm đá bi ok hết. nhưng chưa chuyên nghiệp .\nTevez vô tư , chịu hợp tác mọi tư thế , bảo sao làm vậy ko hề hối thúc.\n\nhình nhé anh em :\n\nupload pictures"
}, {
  "url" : "http://thiendia.com/diendan/threads/chuyen-muc-khoe-lol-vo.1091904/",
  "title" : "PIC - Chuyên mục khoe lol vợ.",
  "unixTime" : 1494923830,
  "imgUrls" : [ "http://server7.upload69.net/images/2017/05/16/IMG_026808675.jpg", "http://server7.upload69.net/images/2017/05/16/IMG_02636eda1.jpg", "http://server7.upload69.net/images/2017/05/16/IMG_0259a2221.jpg", "http://server7.upload69.net/images/2017/05/16/IMG_0261830c4.jpg", "http://server7.upload69.net/images/2017/05/16/IMG_0262260b0.jpg" ],
  "intro" : "Đây là cái lol dâm đãng của vợ em. Mặc dù đã 2 bé rồi nhưng vẫn rất hồng hào. Từ khi sinh bé thứ 2 em nói thực với các bác là em hết cảm giác muốn đi ngoài luôn ạ. Lúc nào cũng chỉ muốn xịt tinh đầy tràn cái lol hồng hào đầy dâm đãng này thôi ạ.\nCác bác cùng em khoe lol vợ nhé.\nVợ em đầu 9x thôi ạ."
}, {
  "url" : "http://thiendia.com/diendan/threads/vo-em-sieu-buom-va-quan-lot-goi-cam.1091900/",
  "title" : "Vợ em - Siêu Bướm và quần lót gợi cảm",
  "unixTime" : 1494923110,
  "imgUrls" : [ "http://server7.upload69.net/images/2017/05/16/image_20170407_155242103879.jpg", "http://server7.upload69.net/images/2017/05/16/image_20170407_1601421daca6.jpg", "http://server7.upload69.net/images/2017/05/16/image_20170407_2121211052e0.jpg", "http://server7.upload69.net/images/2017/05/16/image_20170407_2122251fe1da.jpg", "http://server7.upload69.net/images/2017/05/16/image_20170407_2127171d32ea.jpg", "http://server7.upload69.net/images/2017/05/16/image_20170407_213622282abd.jpg", "http://server7.upload69.net/images/2017/05/16/image_20170407_2139511d52f2.jpg", "http://server7.upload69.net/images/2017/05/16/image_20170407_214719117c83.jpg", "http://server7.upload69.net/images/2017/05/16/image_20170407_2159371f132f.jpg", "http://server7.upload69.net/images/2017/05/16/image_20170407_2205311df085.jpg", "http://server7.upload69.net/images/2017/05/16/image_20170407_22072719d439.jpg", "http://server7.upload69.net/images/2017/05/16/image_20170407_22083915e718.jpg", "http://server7.upload69.net/images/2017/05/16/image_20170408_052849177e6a.jpg", "http://server7.upload69.net/images/2017/05/16/image_20170408_0531351fa31a.jpg", "http://server7.upload69.net/images/2017/05/16/image_20170408_05324611d5e0.jpg", "http://server7.upload69.net/images/2017/05/16/image_20170408_05364714740b.jpg", "http://server7.upload69.net/images/2017/05/16/image_20170408_05535812bbec.jpg", "http://server7.upload69.net/images/2017/05/16/image_20170408_073744168bf6.jpg", "http://server7.upload69.net/images/2017/05/16/image_20170408_07463519e84b.jpg", "http://server7.upload69.net/images/2017/05/16/image_20170408_15181714ee1f.jpg", "http://server7.upload69.net/images/2017/05/16/image_20170408_1522371967cb.jpg", "http://server7.upload69.net/images/2017/05/16/image_20170408_1550251f2f65.jpg", "http://server7.upload69.net/images/2017/05/16/image_20170418_15160115f012.jpg", "http://server7.upload69.net/images/2017/05/16/image_20170418_151757187f49.jpg", "http://server7.upload69.net/images/2017/05/16/image_20170418_152052198ed7.jpg", "http://server7.upload69.net/images/2017/05/16/image_20170418_15215315c479.jpg", "http://server7.upload69.net/images/2017/05/16/image_20170418_1523131a6cd9.jpg", "http://server7.upload69.net/images/2017/05/16/image_20170418_1538081e148d.jpg", "http://server7.upload69.net/images/2017/05/16/image_20170418_1542491d23c9.jpg", "http://server7.upload69.net/images/2017/05/16/image_20170418_15461910ab7a.jpg", "http://server7.upload69.net/images/2017/05/16/image_20170418_155144227684.jpg", "http://server7.upload69.net/images/2017/05/16/image_20170418_15540711af29.jpg", "http://server7.upload69.net/images/2017/05/16/image_20170418_1557111f72ec.jpg", "http://server7.upload69.net/images/2017/05/16/image_20170419_12221415bb93.jpg", "http://server7.upload69.net/images/2017/05/16/image_20170419_122449126e0e.jpg", "http://server7.upload69.net/images/2017/05/16/image_20170420_1339161be819.jpg", "http://server7.upload69.net/images/2017/05/16/image_20170420_134059156f89.jpg", "http://server7.upload69.net/images/2017/05/16/image_20170420_1349481da222.jpg", "http://server7.upload69.net/images/2017/05/16/image_20170420_13510212610e.jpg", "http://server7.upload69.net/images/2017/05/16/image_20170420_1352131a16cf.jpg", "http://server7.upload69.net/images/2017/05/16/image_20170420_1353211048a9.jpg", "http://server7.upload69.net/images/2017/05/16/image_20170420_140713291c2b.jpg", "http://server7.upload69.net/images/2017/05/16/image_20170420_14090118b74d.jpg", "http://server7.upload69.net/images/2017/05/16/image_20170420_1409222bb354.jpg", "http://server7.upload69.net/images/2017/05/16/image_20170420_1409262558ba.jpg", "http://server7.upload69.net/images/2017/05/16/image_20170407_1425211097d1.jpg" ],
  "intro" : "Vc em cũng đã xuát hiện trên TD vài lần rồi, hôm nay có thêm 1 số Pic nữa đóng góp để anh em thị dâm và quay tay.\nCảm ơn anh em đã ủng hộ"
}, {
  "url" : "http://thiendia.com/diendan/threads/rp-ttsh-trang-bong-6657-hai-chu-tuyet-voi-danh-cho-em.1091899/",
  "title" : "Ngon - Trung Sơn-Q.8 - PIC - 500K - RP TTSH Trang Bông 6657 Hai Chữ Tuyệt Vời Dành Cho EM",
  "unixTime" : 1494923008,
  "imgUrls" : [ "http://server7.upload69.net/images/2017/05/16/18516528_458884194463582_1181122573_o2c28d.jpg", "http://server7.upload69.net/images/2017/05/16/18516720_458907444461257_522514789_o15c608.md.jpg", "http://server7.upload69.net/images/2017/05/16/18519301_458907477794587_928889039_o15236f.jpg", "http://s33.postimg.org/c4b0ntqov/avatar_biggrin.gif", "http://matcuoi.com/smilies/yahoo_71.gif", "http://matcuoi.com/smilies/yahoo_2.gif", "http://matcuoi.com/smilies/yahoo_21.gif" ],
  "intro" : "Chào ae thiên địa hội .\ncũng đã lâu rồi mình ko check choách gì cả , thế đéo nào hôm cuối tuần vừa rồi tụ tập với mấy thằng bạn làm có mấy chén diệu ko hiểu sao người cứ rực hết lên . Thế là mò mẫm vào thiendia sem có em nào ngon ko để đi giải quyết cái sinh lí , nói thật là đàn ông ae mình thằng nào có tí men trong người mà chả ngĩ đến gái . Vào kí sự sem thì thấy toàn em trẻ đẹp nhìn em nào cũng hấp dẫn , nhưng sin mãi mà ko đc số của em nào . Đành lòng vào ttsh sem , ngắm nghía lựa chọn mãi cuối cùng mình cũng chọn đc em trang bông mà em đấy lại là gái miền tây nữa chứ , mình thì lại rất thích gái miền tây ăn nói nhẹ nhàng , dễ nge , lại còn ngoan nữa . Không thể chờ đợi đc mình rút luôn điên thoại ra liên lạc cho em nó , và đc em nó cho kai hẹn ở ks bên q8 .Mình liền lấy se phi thẳng một mạch đến chỗ em nó , sau đó một cuộc chiến tình dục giữa mình và em nó đc bắt đầu . Thôi mình xin phép đc kể đến đây thôi cho đỡ mất thời gian của ae và mình đi vào chủ đề chính luôn\n\nNghệ danh : Gái gọi Trang Bông\nMs : 6657\nTuổi : 1994\nloại hàng : Gái gọi sài gòn\nnguyên quán : miền tây\nKhu vực hoạt động : Trung sơn - quận 8\nGiá : 500k / 1 shot\nGiá ks : 80k - 100k\nthời gian phục vụ : trung bình 40 phút 1 shot\nthời gian làm việc : sáng 10h đến 23h đêm .\n\nĐánh giá nhanh :\n\n- Mặt : xinh xắn , vui vẻ , tươi cười .\n- Dáng : cao ráo , thân hình đẹp .\n- body : đẹp , hấp dẫn từ kái nhìn đầu tiên .\n- da : trắng trẻo , thơm phức , mịn màng , ôm rất mát .\n- V1 : to vừa tay , hàng xịn 100% , đầu ti nhỏ , hồng rực , bú bóp thoải mái .\n- V2 : eo ót đâu ra đấy . phẳng , không mỡ thừa .\n- V3 : tròn , đẹp , nhẵn , doggy sướng rên lên .\n- v4 : lông tự nhiên ,gọn gàng , thơm tho , nước thì xài đủ .\n- Sevice : HJ , BJ , liếm ti , mút bi và còn nhiều chỗ khác , vui vẻ , nhiệt tình , kái này ae tự khám phá thêm nhé , vì mỗi người một cảm nhận .\n- Thái độ : nhẹ nhàng , vui vẻ , thân thiện , chụi hợp tác .\n\nLINK TRUNG TÂM SHARE HÀNG\nCÁC BÁC CỨ VÀO ĐÂY LẤY SỐ NHÉ .\n\nhttp://thiendia.com/diendan/threads...-mien-tay-ve-dep-me-hoac-moi-tam-hon.1081130/\n\nSau đây mình có ít ảnh để ae chiêm ngưỡng .\n[/ur"
}, {
  "url" : "http://thiendia.com/diendan/threads/public-voi-vk-iu.1091893/",
  "title" : "Public với vk iu",
  "unixTime" : 1494919931,
  "imgUrls" : [ "https://s3.postimg.org/3pt1illz3/IMG_3380.png", "https://s3.postimg.org/tmmpv7pmn/IMG_3381.png", "https://s3.postimg.org/s8v2zwqdb/IMG_3382.png", "https://s3.postimg.org/8sadddv9b/IMG_3383.png" ],
  "intro" : "upload image online free"
}, {
  "url" : "http://thiendia.com/diendan/threads/vedette-mn-2017-mimi-1395-co-be-diu-dang-va-nhe-nhang-tinh-cam-hon-bao-gio-het.1091892/",
  "title" : "Ngon - Quận 2 - PIC - 500K - [VEDETTE MN 2017] MiMi 1395 - Cô bé dịu dàng và nhẹ nhàng tình cảm hơn bao giờ hết -",
  "unixTime" : 1494919899,
  "imgUrls" : [ "http://server7.upload69.net/images/2017/05/16/1copyaab5a.jpg", "http://server7.upload69.net/images/2017/05/16/2copya0acb.jpg", "http://server7.upload69.net/images/2017/05/16/3copyb3c28.jpg", "http://server7.upload69.net/images/2017/05/16/4copy74e57.jpg", "http://server7.upload69.net/images/2017/05/16/5copy1c7c3.jpg", "http://server7.upload69.net/images/2017/05/16/6copyde990.jpg", "http://server7.upload69.net/images/2017/05/16/7copy758d6.jpg", "http://server7.upload69.net/images/2017/05/16/8copyd9de6.jpg", "http://server7.upload69.net/images/2017/05/16/9copy2b4d4.jpg", "http://server7.upload69.net/images/2017/05/16/10copy4e098.jpg", "http://server7.upload69.net/images/2017/05/16/11copyddde3.jpg", "http://server7.upload69.net/images/2017/05/16/12copy581e8.jpg", "http://server7.upload69.net/images/2017/05/16/13copy2a79c.jpg", "http://server7.upload69.net/images/2017/05/16/14copyc91eb.jpg", "http://server7.upload69.net/images/2017/05/16/15copyd0a5d.jpg", "http://server7.upload69.net/images/2017/05/16/16copy3dfe2.jpg" ],
  "intro" : "Đêm mỏng như làn khói, trời không chút gió, cảm giác trống trải khiến lòng tôi nôn nao khó chịu, làm gì để khỏa lấp màn đêm, làm gì để lòng bớt chơi vơi trong cô quạnh?\n\nVà rồi tôi nhớ đến em, cô gái má hồng duyên dáng với ánh mắt lung linh trong vắt như nước hồ chớm thu. Em nhẹ nhàng trùi mến và ngọt ngào khó cưỡng. Với số điện thoại có được từ một tên bạn nối khố đa tình, tôi biết đến em, rồi từ đó không thể nào không tương tư thầm thương trộm nhớ.\n\nEm đến bên tôi trong một chiều mây đen phủ kín, gió cuốn từng cơn khiến lòng tôi xôn xao như biển động. Chiều giông tố ở đất khách quê người, dẫu là có dùi mài kinh sử rồi cuốc đất cắm dùi, làm việc ở đây mười mấy, hai mấy năm thì những buổi chiều như thế này cũng làm tôi cảm thấy chán nản thê lương. Sài Gòn, nơi phồn hoa đô hội, nhưng trong làn giông bão, nhìn nó ảm đạm đến quặn lòng. Và rồi em đến, như một làn ánh sáng le lói rực rỡ trong đêm tối, và tôi chẳng khác nào con thiêu thân bất chấp mọi thứ lao đến bên em.\n\nVới em, cảm giác mà tôi cảm nhận có thể miêu tả là hệt như cảm xúc khi theo dõi một bộ phim hành động hấp dẫn. Tình tiết đôi lúc nhẹ nhàng sâu lắng, lúc quyết liệt dồn dập, lúc đứt quãng hồi hộp để rồi kết thúc với những pha kinh điển, gay cấn đến đỉnh điểm, cực kỳ mãn nhãn, khiến ta không khỏi hài lòng, bật cười sảng khoái.\n\nÁnh mắt đưa tình, làn môi ngọt lịm, hơi thở lôi cuốn lúc êm đềm lúc rộn ràng. Làn da mát mịn, vòng tay ấm dịu dàng. Em làm cho mọi thứ trở nên dễ chịu, ngọt ngào, mềm mại và quá đỗi ấm áp. Chắc hẳn ai đó một lần được gặp em, cũng như tôi, sẽ si mê em đến điên đảo. Em khiến những thổn thức, bất an của tôi chẳng mấy chốc mà tan biến như chưa hề có.\n\nVà tôi sẵn sàng chia sẻ vì chẳng thể giữ một liều thuốc an thần ngọt ngào như vậy trong bóng tối. Em phải được tỏa sáng và được nhiều người yêu thương. Vậy là ở đây, tôi giới thiệu đến mọi người…\n\nThông tin về em:\nNghệ danh: MiMi\n\nNăm Sinh: 1992\n\nNguồn gốc: Miền Bắc\n\nMã số: 1395\n\nGiá: 500k/s\n\nKhách sạn: 100k/2h đầu\n\nKhu vực hoạt động: An Phú - Quận 2\n\nThời gian làm việc: 10h sáng đến 8h tối\n\nPass: bạn anh Thiên Địa​\nĐánh giá về em:\n\nDáng người: cao ráo, mình dây xinh xắn\n\nMặt: xinh, có nét\n\nNgực: to tròn đẹp, sờ bóp thoải mái\n\nEo: mình dây nên eo chuẩn\n\nMông: to, doggy phê\nBướm: rất đẹp, sạch sẽ thơm tho, vét tốt\nDịch vụ: hôn môi đá lưỡi như người tình, nghệ thuật làm tình rất bài bản, từ từ như mèo ăn cơm ấy, cái gì cũng rất chậm rãi và nhẹ nhàng, Bj, HJ đầy đủ, vét thoải mái, nhận đi Some 2 khách.\nThái độ: Ngoan ngoãn, hợp tác, và rất yêu nghề. Kỹ thuật của MiMi và thái độ của em như thế thì hoàn toàn xứng đáng để check.\n\nMột số hình ảnh cho anh em thị dâm."
}, {
  "url" : "http://thiendia.com/diendan/threads/vk-e-nhu-nay-co-duoc-goi-la-dam-khong.1091891/",
  "title" : "PIC - vk e như này có được gọi là dâm không",
  "unixTime" : 1494919700,
  "imgUrls" : [ "http://66.70.164.147/images/2017/05/16/201705161358088e5e5.jpg", "http://66.70.164.147/images/2017/05/16/IMG_20170331_0844573fc65.jpg", "http://66.70.164.147/images/2017/05/16/IMG_20170331_0845201795b.jpg", "http://66.70.164.147/images/2017/05/16/IMG_20170502_1427015227c.jpg", "http://66.70.164.147/images/2017/05/16/IMG_20170514_22530900fde.jpg", "http://66.70.164.147/images/2017/05/16/IMG_20170514_22531181122.jpg", "http://66.70.164.147/images/2017/05/16/IMG201605031626459c45b.jpg" ],
  "intro" : "vk ck em ở xa nên nhiều khi ít cơ hội gặp được nhau, gặp nhau thì không thể nói hết sự máu lửa và đam mê, dục vọng lúc nào cũng dữ dội như sóng.\ncác bác chiêm ngưỡng coi máy móc như này có đạt điểm để đồng dâm quay tay không nha.\ne đang dụ vk some cho phong phú, mà cũng đang ngập ngừng, còn nhiều hình và video, các bác ủng hộ cho e có tinh thần post.\n[/url] [/IMG]"
}, {
  "url" : "http://thiendia.com/diendan/threads/em-ghe-nhi-dam-dang.1091889/",
  "title" : "Em ghệ nhí dâm đãng",
  "unixTime" : 1494919280,
  "imgUrls" : [ "http://66.70.164.147/images/2017/05/16/C360_2017-05-16-14-07-03-64842ed5.jpg", "http://66.70.164.147/images/2017/05/16/received_7882108213405365bfe5.jpg", "http://66.70.164.147/images/2017/05/16/received_788211004673851f78fd.jpg", "http://66.70.164.147/images/2017/05/16/DSC_0062f60ef.jpg", "http://66.70.164.147/images/2017/05/16/DSC_0061005c0.jpg", "http://66.70.164.147/images/2017/05/16/C360_2017-05-16-14-06-22-416d105c.jpg", "http://66.70.164.147/images/2017/05/16/C360_2017-05-16-14-05-51-219b3ce3.jpg", "http://66.70.164.147/images/2017/05/16/C360_2017-05-16-14-06-10-918ffd98.jpg" ],
  "intro" : "Tham gia thiên địa lâu... H có e ghệ nhí dăng lên cho ae nhận xét... Thích thì lần sau up nhiều hơn... Hẹn sẽ có outdoor và đường hậu trước sau cho ae.. Kkk\n\n​\nThanks đã xem.."
}, {
  "url" : "http://thiendia.com/diendan/threads/hotgirl-cafe.1091877/",
  "title" : "Hotgirl Cafe",
  "unixTime" : 1494916335,
  "imgUrls" : [ "https://68.media.tumblr.com/8f917458e391a153dc653885fc272d96/tumblr_opk8qoeYT71wp9iyto4_500.jpg" ],
  "intro" : ""
}, {
  "url" : "http://thiendia.com/diendan/threads/hotgirl-cafe.1091877/",
  "title" : "Hotgirl Cafe",
  "unixTime" : 1494916335,
  "imgUrls" : [ "https://68.media.tumblr.com/8f917458e391a153dc653885fc272d96/tumblr_opk8qoeYT71wp9iyto4_500.jpg" ],
  "intro" : ""
} ]