[ {
  "url" : "http://thiendia.com/diendan/threads/chieu-sung-suong-voi-co-ban-shemale-hn.1165950/",
  "title" : "PIC - BẮC - Chiều sung sướng với cô bạn shemale HN",
  "unixTime" : 1528408800,
  "imgUrls" : [ "http://server8.upload69.net/images/2018/05/08/IMG_20180508_18085828ed195413df0ac11.jpg", "http://server8.upload69.net/images/2018/05/08/IMG_20180508_180902141785e87f95caa4b.jpg", "http://server8.upload69.net/images/2018/05/08/IMG_20180508_1809081f8a11201f3f8fac3.jpg" ],
  "intro" : "Chả là lướt qua đọc được topic của some rất li kì của bạn shemale trong rạp phim http://thiendia.com/diendan/threads/chuyen-ve-lan-dau-some-la-thich-hihi.1163130/ mà chim cò cửng hết cả lên, tự động phải thò tay quần sóc sóc vài cái cho chim đỡ nứng.Mình thì chưa có kinh nghiệm nhiều với shemale mà chỉ là sở thích thầm kín thế nhưng cảm giác thèm muốn đã chiến thắng sự ngại ngùng. Thế là quyết tâm xin số zalo add friend để có cơ hội được gặp dâm nữ này ngoài đời xem thực hư như thế nào.\n\nVừa add zalo thì một lúc lâu sau mới được accept,mình và bạn ấy nói chuyện qua loa xã giao được một hai câu thì hẹn ra một quán cafe để nch nhiều hơn. Mình cũng là lần đầu chơi shemale nên rất muốn tìm hiểu kỹ lưỡng thêm chút\n\nHẹn ra một quá cafe, hai đứa chọn một bàn ở góc khuất để nói chuyện. Ấn tượng đầu tiên là người hơi chắc nhưng được cái mông và ngực rất hấp dẫn, mặt thì cũng xinh bình thường ( mình thích kiểu cực kì nữ tính nên đánh giá phần này hơi khó)\nBạn ấy lúc đầu nói chuyện thì khá là lạnh lùng làm mình cũng chả biết bắt đầu câu chuyện như thế nào cho hợp lí, không khí khá chán. Nhưng mà đúng lúc đó thì ting ting tiếng zalo nhảy lên hai bức ảnh. Hóa ra là bạn ấy đã gửi hai bức hình nóng cho mình\n\nGiữa quán cafe mà thấy hai hình ảnh một shemale với chiếc áo lưới, đúng hai sở thích của mình. thêm vào đó mông và núm vú dựng đứng của bạn ấy rất dâm. THấy mình bất ngờ với nứng như thế bạn ta còn đổ thêm dầu vào lửa bằng cách liếm môi với kéo ghế ngồi cạnh bên mình lấy tay xoa xoa đũng quần. Cảm giác tích tụ bao lâu muốn bùng nổ.\nVội thanh toán tiền cafe dẫn vào nhà nghỉ ngay lập tức. Không cần đợi tắm rửa mình đè bạn ấy ra kéo tụt bộ đồ để lộ ra bộ ngực căng bóng. Mình mân mê bộ ngực hôn nút môi được một chút thì bạn ta đè mình ra tụt quần kéo con cặc sắp phát nổ ra bú.\n\nChắc với kinh nghiệm từng là đàn ông mà cách bú của bạn ấy rất cuốn làm mình out ngay trong sung sướng .thậm chí out ròi mà bạn ấy không dừng bú là tinh trùng rơi vãi hết bụng mình. mình tranh thủ chụp lại tâm duy nhất\n\nThấy bạn ấy còn liếm hết chỗ tinh trùng ở bụng, sau đó thì mình quá sướng cũng bỏ kệ điện thoại ra một bên lao vào 69 rồi doggy 2 giờ liên tục.\n\nMột kỉ niệm shemale rất sung sướng"
}, {
  "url" : "http://thiendia.com/diendan/threads/van-cute-0526-gai-moi-lon-cap-vu-tuyet-dep-sv-tot.1165881/",
  "title" : "300K - Xã Đàn - Vân Cute 0526 Gái mới lớn, cặp vú tuyết đẹp, SV tốt",
  "unixTime" : 1528408800,
  "imgUrls" : [ "http://server8.upload69.net/images/2018/05/05/IMG_2242ed03d1ac93e28467.jpg", "http://server8.upload69.net/images/2018/05/05/IMG_2243888699d3298f0e87.jpg", "http://server8.upload69.net/images/2018/05/05/IMG_2244e834473f235ed702.jpg", "http://server8.upload69.net/images/2018/05/05/IMG_22500a0fb17db16da917.jpg", "http://server8.upload69.net/images/2018/05/05/IMG_2251cbfed9831102c9ec.jpg", "http://server8.upload69.net/images/2018/05/05/IMG_225281932462153cb592.jpg", "http://server8.upload69.net/images/2018/05/05/IMG_2253652e0e24c86bbf1e.jpg", "http://server8.upload69.net/images/2018/05/05/IMG_2254789fc49af7cde50d.jpg", "http://server8.upload69.net/images/2018/05/05/IMG_22561c7043d8c8a9185b.jpg", "http://server8.upload69.net/images/2018/05/05/IMG_23296dde6b8f3a4c5a27.png", "http://server8.upload69.net/images/2018/05/05/IMG_2331f2949f33f732bfb2.png", "http://server8.upload69.net/images/2018/05/05/IMG_2332990fb56c33332fa0.png", "http://server8.upload69.net/images/2018/05/05/IMG_2334667f2369b5906f55.png" ],
  "intro" : "Vân Cute 0526\n300k/shot\nGái gọi Hà nội\n0167 557 0526\nlấy số ở Thiendia\nNhà nghỉ120k/2h\nXã Đàn - KLM\nKhông rõ\nXuất xứKhông rõ\nCaoDáng xôi thịt, ăn mặc sexy hấp dẫn\nDamịn màng\nMặtXinh xắn, cute, có nét duyên\n\ncăng, bóp rất đẫy tay 7đ\n\nEoEo ót có chút mỡ thừa nhưng mà ôm thích\nMông cong nhìn ngon lắm, mình ko chơi doggy nhưng úp thìa thìa khá là phê\nBímSạch sẽ thơm tho, lông lá tự nhiên, có chút cavat\n\nServiceHôn môi\nVét máng\nHJ, BJ, tương đối hợp tác, bài bản\n35 phút / lần phọt\n13h - 21h hàng ngày\nĐánh_giárất ngoan ngoãn chiều khách không láo, không tráo hàngLink report tham khảo:\nhttp://thiendia.com/diendan/threads...cap-cu-dep-tuyet-de-thuong-sevit-tot.1164920/\n\nhttp://thiendia.com/diendan/threads/van-cute-0526-mot-chieu-mua-ngon-chim.1165042/"
}, {
  "url" : "http://thiendia.com/diendan/threads/co-the-cho-e-hoi-dv-cua-em-bi-lam-sao-ko-a.1165843/",
  "title" : "Có thể cho e hỏi dv của em bị làm sao ko ạ",
  "unixTime" : 1528408800,
  "imgUrls" : [ "https://sv1.uphinhnhanh.com/images/2018/05/08/Capture.jpg" ],
  "intro" : "Sáng e ngủ dậy thì để ý thấy 4 cái cục như này, nó không hề đau ạ\nEM ko hề qhtd gì cả đâu, chỉ quay tay thôi"
}, {
  "url" : "http://thiendia.com/diendan/threads/ve-dep-cua-shemale-p8.1165812/",
  "title" : "PIC - Vẻ đẹp của shemale (p8)",
  "unixTime" : 1528408800,
  "imgUrls" : [ "http://server8.upload69.net/images/2018/05/08/TranSexJapan-NakazawaChulin-0002-1634848a4b0f8604ee.jpg", "http://server8.upload69.net/images/2018/05/08/TranSexJapan-NakazawaChulin-0002-1550de962a0c2c560a.jpg", "http://server8.upload69.net/images/2018/05/08/TranSexJapan-NakazawaChulin-0002-1445474f9a89a661e8.jpg", "http://server8.upload69.net/images/2018/05/08/TranSexJapan-NakazawaChulin-0002-11f9c15c3528aa133a.jpg", "http://server8.upload69.net/images/2018/05/08/TranSexJapan-NakazawaChulin-0002-09eb73453cafb6dffb.jpg", "http://server8.upload69.net/images/2018/05/08/TranSexJapan-NakazawaChulin-0002-08d14debec8703a0e9.jpg", "http://server8.upload69.net/images/2018/05/08/TranSexJapan-NakazawaChulin-0002-0715d64b32744e028f.jpg", "http://server8.upload69.net/images/2018/05/08/TranSexJapan-NakazawaChulin-0002-05bc028d34160340a6.jpg", "http://server8.upload69.net/images/2018/05/08/TranSexJapan-NakazawaChulin-0002-046a4665240fb59afc.jpg", "http://server8.upload69.net/images/2018/05/08/TranSexJapan-NakazawaChulin-0002-037f8b107b77c0ef18.jpg", "http://server8.upload69.net/images/2018/05/08/TranSexJapan-NakazawaChulin-0002-021fea3867fff8f807.jpg", "http://server8.upload69.net/images/2018/05/08/TranSexJapan-NakazawaChulin-0002-017f457e6974dadbc9.jpg", "http://server8.upload69.net/images/2018/05/08/164af3c6b9dc673918.jpg", "http://server8.upload69.net/images/2018/05/08/15cb574a147db39441.jpg", "http://server8.upload69.net/images/2018/05/08/1480ada1b2fb93bb30.jpg", "http://server8.upload69.net/images/2018/05/08/130353722ede41aa6a.jpg", "http://server8.upload69.net/images/2018/05/08/12-1097e42b8971733cd.jpg", "http://server8.upload69.net/images/2018/05/08/11-1194f5f19fd6a5dc4.jpg", "http://server8.upload69.net/images/2018/05/08/10-17c9f524cda5d13e5.jpg", "http://server8.upload69.net/images/2018/05/08/09-150eac74be4a9f460.jpg", "http://server8.upload69.net/images/2018/05/08/08-19817dcfd0c8db82f.jpg", "http://server8.upload69.net/images/2018/05/08/07-1f4215633bbcbed97.jpg", "http://server8.upload69.net/images/2018/05/08/06-27b2208b5b03556d1.jpg", "http://server8.upload69.net/images/2018/05/08/05-203b10e670801b2e8.jpg", "http://server8.upload69.net/images/2018/05/08/04-26728935b04726959.jpg", "http://server8.upload69.net/images/2018/05/08/03-2a67245471882996f.jpg", "http://server8.upload69.net/images/2018/05/08/02-2a6e074158d8d7db1.jpg", "http://server8.upload69.net/images/2018/05/08/01-22ea2197b8429727d.jpg", "http://server8.upload69.net/images/2018/05/08/06-183e41a0548524fd9.jpg", "http://server8.upload69.net/images/2018/05/08/05-13b61ed5e006eed51.jpg", "http://server8.upload69.net/images/2018/05/08/04-1c7b175280510b211.jpg", "http://server8.upload69.net/images/2018/05/08/03-12e4046480129542e.jpg", "http://server8.upload69.net/images/2018/05/08/02-120b4d7b4beae2210.jpg", "http://server8.upload69.net/images/2018/05/08/01-1df8a414ba797b38c.jpg", "http://server8.upload69.net/images/2018/05/08/12d6149842c65818c4.jpg", "http://server8.upload69.net/images/2018/05/08/11e36f3231d0e58911.jpg", "http://server8.upload69.net/images/2018/05/08/105e02f233e5a6edbe.jpg", "http://server8.upload69.net/images/2018/05/08/095af42fdfc70af7a3.jpg", "http://server8.upload69.net/images/2018/05/08/08196054c1ee71c8d0.jpg", "http://server8.upload69.net/images/2018/05/08/0755c89980379e3b98.jpg", "http://server8.upload69.net/images/2018/05/08/06672415d3ee26a16e.jpg", "http://server8.upload69.net/images/2018/05/08/05c4cc0f7045cfab96.jpg", "http://server8.upload69.net/images/2018/05/08/04ce586c23e225d380.jpg", "http://server8.upload69.net/images/2018/05/08/0360b63c7815aa017d.jpg", "http://server8.upload69.net/images/2018/05/08/02baa5867caff9a7c9.jpg", "http://server8.upload69.net/images/2018/05/08/019e5f9f2ba005b0b6.jpg" ],
  "intro" : "Sau 1 thời gian bỏ xó chủ đề vì chả ai quan tâm nhưng vì đam mê nên mình quyết định mở lại.\nBây giờ mình thích là mình đăng nên chả quan tâm mọi người có thích hay ko. Ahihi"
}, {
  "url" : "http://thiendia.com/diendan/threads/hom-nay-xuong-toc-cho-gon-gang.1165489/",
  "title" : "PIC - BẮC - Hôm nay xuống tóc, cho gọn gàng",
  "unixTime" : 1528322400,
  "imgUrls" : [ "http://server8.upload69.net/images/2018/05/06/6F611CAD-F4C0-46CB-95A1-5F5414AE0EC5-2255-000002DA72E418868ed897eaf7110138.jpg", "http://server8.upload69.net/images/2018/05/06/F315DFEE-83A6-4763-9E60-04CD70DD9FEC-2255-000002DA7D3386AD27c86bb91cab9e94.jpg" ],
  "intro" : "Cuối tuần xách cờ him đi chơi.\nNhân tiện bạn nèo muốn giao lưu inbox nhé. Hôm nay cạo trắng hếu rồi\nHOÀNG MAI THÔI\n[/url] [/IMG]"
}, {
  "url" : "http://thiendia.com/diendan/threads/massage-nuru-tokyo-243-quan-hoa.1165190/",
  "title" : "Massage - Chuẩn - Massage Nuru Tokyo 243 Quan Hoa",
  "unixTime" : 1528236000,
  "imgUrls" : [ "http://server8.upload69.net/images/2018/05/04/IMG_20180505_0324480500a7e1f4cb05dc.jpg", "http://server8.upload69.net/images/2018/05/04/IMG_20180505_03245114c06c6c0cbb8b1d.jpg", "http://server8.upload69.net/images/2018/05/04/IMG_20180505_032412fe9374e46a19dc96.jpg", "http://server8.upload69.net/images/2018/05/04/IMG_20180505_0324163a575795914bbbc0.jpg", "http://server8.upload69.net/images/2018/05/04/IMG_20180505_0324198b39182477554d68.jpg", "http://server8.upload69.net/images/2018/05/04/IMG_20180505_03252776f434a4037e9c5d.jpg", "http://server8.upload69.net/images/2018/05/04/IMG_20180505_0324349e6af13a18e463d7.jpg", "http://server8.upload69.net/images/2018/05/04/IMG_20180505_032437961da3c295466428.jpg", "http://server8.upload69.net/images/2018/05/04/IMG_20180505_032442710d4205d63b2593.jpg", "http://server8.upload69.net/images/2018/05/04/IMG_20180505_032445ab54aa6deac48d36.jpg" ],
  "intro" : "TOKYO VIP MASSAGE tuy là mở cũng lâu rồi, nhưng mới vừa được đổi chủ,đổi quán lý và có rất nhiều em nv mới trẻ. Với nhiều năm trong nghề nên nắm bắt được thị hiếu và những loại hình đang Hot nhất hiện nay.\nĐây là cở sở được đầu tư kỹ về trang thiết bị mới nhất, sang trọng, nội thất theo phong cách châu âu đầy đủ hệ thống xông hơi, xông ướt, bể sục.\nVới đội ngũ nhân viên được tuyển chọn kỹ lưỡng ngoại hình ngon, xinh đẹp trẻ trung. Các em đều được đào tạo bài bản về kỹ năng massage, yêu cầu đấm bóp phải chuẩn, không bỏ bài, không làm qua loa và các em làm tốt các kỹ thuật như : Nóng lạnh, bạc hà, Nuru massage Thái, coca khiến các em như những nữ thần JAV đảm bảo khiến anh em quên đường về\nChúng tôi có những gói\n- Vip 1 - Giá 500K: Xông hơi thảo dược, ngâm chân muối khoáng và gừng, tắm vip sữa dê/tắm vip ngọc trai; massage body toàn thân với tinh dầu thái (hoặc sữa chua. – tùy chọn)\n- VIP 2 – Giá 700K: Bao gồm giống VIP 1 nhưng là 4 tay\nKhuyến mãi: Đi nhóm 5 người được giảm 50%; đi nhóm 3 ngươi được giảm 30% tiền vé các anh nhé.\n\nGói tinh dầu Thái/Nhật, Chúng tôi đảm bảo sử dụng sản phẩm rõ nguồn gốc xuất xứ, chiết suất từ thành phần thiên nhiên đảm bảo an toàn cho da, CỰC KỲ TRƠN và không để lại mùi, vị ! chắc chắn KHÔNG CHO VỢ HAY GẤU “đánh hơi” được. Và tên hãng gel được sử dụng ỏ đây cũng là NURU gel. Ở gói này, sẽ sử dụng giường ngủ (chứ ko phải là giường massage như ở Oasis, saukura), sau đó đổ gel lên người khách và trườn bò xin cam đoan là CHUẨN JAV.\nVề mức tip thì:\n500K: Trườn Nuru, BJ, coca, nóng lạnh\n700K: nếu các em nó tắm chung với các anh em + Trườn Nuru, BJ, coca, nóng lạnh\nHiện cơ sở mới mở nên nhân viên có tầm 20 nv và có mấy em xinh chuẩn xin giới thiệu trước với anh em:\nEm số 09: mặt xinh, dáng cao ráo, ngực chắc, service cực dâm: chống chỉ định với những anh yếu sinh lý\nEm số 11: mặt xinh teen, dáng cao, ngực đẹp căng to tròn\nEm 14: mặt xinh, da trắng, dễ thương, service nhẹ nhàng\nEm 17: mặt xinh, ngực rất to (không được chắc lắm do quá to), nói chuyện nhỏ nhẹ, tình cảm\nSố 20: nhìn như thiên thần, chỉ muốn làm người yêu\nEm số 38: Mặt xinh dễ thương, ngực vừa phải, nhẹ nhàng tình cảm\nCác anh em liên hệ qua zalo: 0914906555 để được giảm giá và xem ảnh các nv\nSau đây là một số hình ảnh về cơ sở chúng tôi."
}, {
  "url" : "http://thiendia.com/diendan/threads/thu-thanh-xuan-sieu-pham-lo-tit-full-sv.1165399/",
  "title" : "PIC - 200K - Thanh Xuân - Ngon - Thu Thanh Xuân siêu phẩm lỗ tít, full sv",
  "unixTime" : 1528236000,
  "imgUrls" : [ "http://server8.upload69.net/images/2018/05/06/IMG_0035fe7e46be04c2725d.jpg", "http://server8.upload69.net/images/2018/05/06/IMG_00382b3327c221231502.jpg", "http://server8.upload69.net/images/2018/05/06/IMG_0044118f11b03c7cb4cb.jpg", "http://server8.upload69.net/images/2018/05/06/IMG_00461cc3cf9e8541f79f.jpg", "http://server8.upload69.net/images/2018/05/06/IMG_0047be29932c685ed512.jpg", "http://server8.upload69.net/images/2018/05/06/IMG_0050d9fad2f834e8fd58.jpg", "http://server8.upload69.net/images/2018/05/06/IMG_0051142f298fccc3f093.jpg", "http://server8.upload69.net/images/2018/05/06/IMG_0054d9a8036988ee153e.jpg" ],
  "intro" : "Cũng lâu ko đi check choác hàng họ 1 phần vì cv cũng bận nhưng cái chính là dạo này phải chạy thêm hết Ship đồ lại thêm tí Grab nọ kia nên kinh tế nó eo hẹp, nhưng lâu ko xả cũng bí bách, nên lại đi xin xỏ con thỏ các kiểu thì có dc số em nó, alo em và có ngay tí ảnh check choác về cho anh em tận hưởng\n\nNghệ danh:\n\nGÁI GOI: HÀ THU ms 926\n\nLOẠI HÀNG: GÁI GỌI HÀ NỘI\n\nGiá:200k / 1 Lần phọt phẹt\n\nGiá nn/ ks: 100k/2h\n\nThời gian: cam kết ít nhất 40p\n\nKhu vực thường xuyên hoạt động: Thanh Xuân\n\nThời gian làm việc hàng ngày: từ 7h sáng đến 10h đêm. Ko qua đêm\n\nĐánh giá thông tin:\n\nMặt: Dâm,dễ nhìn có tí chân quê\n\nBody: Đầm,ôm sướng\n\nVú : vừa tay,mềm,đầu ti hơi thâm,bóp sướng nhưng hơi nhão rồi\n\nBụng thì có tí mỡ không thể tránh khỏi rồi\n\nMông mẩy, to tròn, nẩy tanh tách, trắng tròn\n\nBím vẫn còn tí khít, nhưng thích nhất quả siêu phẩm lỗ nhị\n\nKỹ thuật SV PRO,có cả BJ Nóng Lạnh đáp ứng nhu cầu tất cả\nService cam kết: HJ, BJ, Lỗ Nhị, thích có cả phụ kiện đi kèm hỗ trợ ae....\n\nThái độ phục vụ : chuẩn nhiệt tình,ngoan ngoãn,cam kết hài lòng những vị khách khó tính nhất\nCó tí ảnh check cho ae tham khảo"
}, {
  "url" : "http://thiendia.com/diendan/threads/thu-trang-3740-hang-giai-nhiet-mua-he-cho-anh-em-mat-xinh-dam-di-bj-nong-lanh-lam-tinh-dinh-cao.1165279/",
  "title" : "PIC - 250K - NKT - Ngon - THU TRANG 3740 HÀNG GIẢI NHIỆT MÙA HÈ CHO ANH EM, MẶT XINH, DÂM ĐĨ,BJ NÓNG LẠNH, LÀM TÌNH ĐỈNH CAO",
  "unixTime" : 1528236000,
  "imgUrls" : [ "http://server8.upload69.net/images/2018/05/06/16f966d011ff97595.md.jpg", "http://server8.upload69.net/images/2018/05/06/2072e4c05cffdf87f.md.jpg", "http://server8.upload69.net/images/2018/05/06/35198e8b4de9208c9.md.jpg", "http://server8.upload69.net/images/2018/05/06/4ab0d9967d73a3a2d.md.jpg", "http://server8.upload69.net/images/2018/05/06/68b5246bc44d4813b.md.jpg", "http://server8.upload69.net/images/2018/05/06/7bfe8104f90f757b4.md.jpg", "http://server8.upload69.net/images/2018/05/06/872413f5a8748edd1.md.jpg", "http://server8.upload69.net/images/2018/05/06/9ff0fd140e0f550b5.md.jpg" ],
  "intro" : "Mùa hè đến rồi, có món quà cho anh em giải nhiệt mùa hè, lần đầu tiên lên sóng, AE bớt chút thời gian qua ủng hộ nhé!\nTHÔNG TIN EM GÁI\n\nGái gọi : Thu Trang\nMs 3740\nLoại Hàng: Gái Gọi Hà Nội\nSố ĐT: 096xxx3740\nPass Bạn Anh Thiên Địa Hội\nRổ giá : 250/1 shot ( có nhận shot2, nhận some 2 nam 1 nữ)\nThời gian làm việc 11h sáng đến 1 h đêm\nThời gian phục vụ tối thiểu 30 phút\nGiá nhà nghỉ 100k/2h đầu trong ngõ sạch sẽ rất kín đáo\nKhu vực hoạt động : Nguyễn Khánh Toàn\nMặt xinh, bầu bĩnh, mắt dâm đĩ, trang điểm đẹp\nBody 1m65, hơi thừa cân 1 chút, to đầm, chắc nịch\nMôi rất mềm, bj tê đầu khấc luôn\nNgực rất đẹp chưa sinh nở lần nào, đầu ti thụt, rất căng, bóp bú thoải mái\nEo : cái này hơi thừa mỡ, nhưng ôm rất chắc\nMông, tròn to, căng đét,doggy phê lòi, tanh tách\nBím sạch sẽ, rất bót,chỉ có 1 chút cavats nhé, nước nôi tràn trề, lông lá cắt tỉa rất gọn gàng\n\nDịch vụ cam kết : Hôn môi, vét máng, đá bi, liếm nhị, 6996, đầy đủ, hợp tác mọi tư thế với anh em checker\nDịch vụ không cam kết : CIA + QUA ĐÊM\n\nSkin: Hàng mới tinh, em nó có đầy đủ skin của 1 dâm nữ, lần sờ trườn bò, bj ngập đốc, nóng lạnh đầy đủ nếu anh em yêu cầu, làm tình rất bài bản, chịu khó thay đổi tư thế để hài lòng checker nhất quả mông to của em rất hợp với anh em fan của doggy\n\nChúc anh em giải nhiệt vui vẻ bên gái mới lên sóng"
}, {
  "url" : "http://thiendia.com/diendan/threads/ha-noi_e-lan-dau-va-mong-dc-ae-quan-tam.1164773/",
  "title" : "Đê La Thành - Hà Nội_e lần đầu và mong đc ae quan tâm ^^",
  "unixTime" : 1528149600,
  "imgUrls" : [ "http://server8.upload69.net/images/2018/05/04/491B625A-E66F-45CF-881F-317681246958277b855dc4fbf468.jpg", "http://server8.upload69.net/images/2018/05/04/5C524915-82AC-4E45-80A9-580E4AE3B59A3ba424c75d141a14.jpg", "http://server8.upload69.net/images/2018/05/04/BE2FF600-F19A-4C58-AC02-C841E45D7640fb3dc31f642ace6b.jpg", "http://server8.upload69.net/images/2018/05/04/9F5AC37D-151C-42D5-AA29-40C83EBD5E1A4c32c4f8ed00735b.jpg", "http://server8.upload69.net/images/2018/05/04/A7C7D49C-839D-407E-85E4-3F5E3397AA2D9fbe5d7f8668ff7d.jpg", "http://server8.upload69.net/images/2018/05/04/16C2CCEE-B840-45EB-9305-8C8C75F1080C1ade996c15340a2b.jpg" ],
  "intro" : "Góc nhỏ:\nE là trai thẳng 100% nhưng do nhiều khó khăn lẫn áp lực trong cuộc sống nên e xin phép được phục vụ các a có nhu cầu nhé ^^\nVì e là boy nhưng vì hoàn cảnh nên các a yên tâm e hiểu và biết việc đồng tiền và trách nhiệm nó ntn\nE nhận thông qua nc trên zalo a nhé ^^ a nào quan tâm ib e nha ^^hihi.\nMong các ae đọc kỹ rồi ib tránh tình trạng ib e cho số rồi lại kêu e lừa đảo nhé\nThak ae đã xem ^^"
}, {
  "url" : "http://thiendia.com/diendan/threads/tra-bai-than-dam-khanh-ninh-5674-cam-giac-incest-voi-service-sieu-khung-full-cua-full.1164899/",
  "title" : "PIC - 200K - Từ Liêm - Ngon - Trả bài thần dâm Khánh Ninh 5674 Cảm giac INCEST với Service Siêu Khủng Full của Full",
  "unixTime" : 1528149600,
  "imgUrls" : [ "http://server8.upload69.net/images/2018/05/05/2018-05-05-09.12.14-14cb7d43fc3dc981c.jpg", "http://server8.upload69.net/images/2018/05/05/2018-05-05-08.50.26-1e6223c6ea8eefeea.jpg", "http://server8.upload69.net/images/2018/05/05/2018-05-05-08.50.25-147f236d14d3e2ec5.jpg", "http://server8.upload69.net/images/2018/05/05/2018-05-05-08.50.22-1570c5ac4d9737881.jpg", "http://server8.upload69.net/images/2018/05/05/IMG_20180504_202114_HDR67c2ab138eccf30f.jpg", "http://server8.upload69.net/images/2018/05/05/2018-05-05-08.50.19-116af5f33c3d4d99f.jpg" ],
  "intro" : "Thân chào các toàn thế các anh em Hội Thiên Địa !\nEm Khánh Ninh này thì không có gì xa lạ với các anh em của Hội rồi trước đây cũng đã có một số RP về em nó nên mình không nói dài dòng nữa, nhưng thực sự sau check Khánh Ninh cảm giác quá hài lòng với SV của em nó nên dành chút thời gian ngồi viết RP để chi ân những đóng góp của em đã phục vụ biết bao con chim của các anh em Hội Thiên Địa chúng ta. Và cũng là để giới thiệu đến các anh em chưa gặp được em nó.\nCó số em Khánh Ninh rất lâu rồi nhưng do bận công việc với lại cũng đã có Gấu chó nên cũng không có nhiều thời gian để check em nó. Chiều nay cuối tuần có việc mạn khu cầu giấy sau khi xử lý công việc xong xuôi lang thang không biết làm gì thì nhớ đến em hàng Khánh Ninh khu vực Đê La Thành Full SV kèm cả WC mà chưa có dịp check. Lòng lại bồi hồi nghĩ đến cảm giác chơi lỗ nhị không phải em hàng nào cũng có.\nQuá trình Contac và được cái hẹn với em nó ở bãi đáp mới (Lưu ý em nó mới chuyển về làm ở khu Đỗ Đức Dục gần khách sạn Marriott) . em ok kèm theo lời nhắn anh tắm rửa sạch sẽ để em phục vụ cho chu đáo nhé. nghe thấy là ưng rồi hihi.\nLấy phòng Vừa tắm táp sạch sẽ xong thì có tiếng gõ cửa nhẹ nhàng đúng 15p từ khi lấy phòng thời gian như vậy là rất ok. Mở cửa thì đập vào mắt là một em ăn mặc kín mít đeo khẩu trang người nhỏ nhỏ tầm 1,5, ấn tượng ban đầu thấy hơi hụt hẫng vì em hơi nhỏ và ăn mặc khá quê. Nhưng MB giá rẻ mà không đòi hỏi nhiều được quan trọng là check SV của em như thế nào thôi.\nCũng hơi buồn buồn nhưng em lại chủ động nói chuyện hỏi han rất tình cảm nên cũng thấy thoải mái. Vào phòng thì em cũng xin phép làm vệ sinh chút để chiến đấu, điểm này cộng thêm cho em về khoản thời gian và sạch sẽ.\nBắt đầu từ đây mình chỉ việc nằm trên giường và hưởng thụ cái SV full của em, cảm giác như một ông vua con muốn gì được lấy em làm việc cần mẫn bú mút lưỡi em lướt nhẹ từ chân đến WC rồi lại từ WC đến chân đi đến đâu là rùng mình đến đấy cảm giác quá phê, rồi cái lưỡi ẩm ướt của em ngoáy vào WC rất điêu luyện. em BJ dọn WC tầm 10p chịu không nổi sợ out mất thì phí vì chưa được Check lỗ nhị của em. Vậy là đeo bao vào và chiến đấu với lỗ nhị của em thôi.\nSau đây là một số hình ảnh trong lúc chiến đấu để các pro thị dâm.\n\nTHÔNG TIN VÀ ĐÁNH GIÁ\nGái gọi : Khánh Ninh\nGiá : 200/shot, 400K/2shot\nSố điện thoại:\nSĐT : 097xxx5674\nPASS: Lấy số thiên địa\nGía nhà nhỉ : 80-100k / 2h phòng đẹp sạch sẽ\nKhu vực HĐ : Đỗ Đức Dục gần KS Marriott\nTime làm việc : từ 09h00 đến 22h đêm\nCam Kết 100% Hàng Chuẩn . Không Tráo hàng\nMặt : Dâm đãng, cảm giác INCEST\nV1 : vú to , vừa tay , săn chắc bú thích\nV2 : Hơi có mỡ vẫn còn săn chắc, mịn màng\nV3 : mông to chắc, doggy thích\nBym : sạch sẽ thơm tho, nước nôi đủ dùng\nService : Full thích gì cứ bảo em nó chiều tất\nDV cam kết\n+ Thời gian phục vụ: Thoải mái, tối thiểu 30'\n+ Hôn hít : có\n+ Hj : có\n+ Bj : có, có cả BJ nóng lạnh phê hết người\n+ Tevet : có\n+ WC : Có\n+ CIA: Có\n+ Lỗ nhị: Có\nKết Luận : Một em hàng với SV quá tuyệt vờ thích hợp với Bác nào thích Full SV, SV của em nó quá đa dạng trong một lần không thể sử dụng hết được, sẽ còn gặp lại em nhiều lần nữa để từ từ hưởng thụ. Đồng dâm nào cùng thích SV của em nó thì cứ đặt gạch hoặc inbox để lấy số nhé."
} ]