[{"url":"http://thiendia.com/diendan/threads/gai-goi-quan-10-van-du-ms-0776-chu-nghia-phon-thuc-ngoan-ngoan-nhiet-tinh.1033203/","title":"Quận 10 - 500K - gái gọi quận 10 - Vân Du - ms : 0776 - Chủ nghĩa phồn thực, ngoan ngoãn nhiệt tình","unixTime":1473230724,"imgUrls":["http://server7.upload69.net/images/2016/09/05/1473094303372_29050e6b91.jpg","http://server7.upload69.net/images/2016/09/05/1473094303374_2905130002.jpg","http://server7.upload69.net/images/2016/09/05/1473094303375_2905271e4b.jpg","http://server7.upload69.net/images/2016/09/05/1473094303378_29054a26ca.jpg","http://server7.upload69.net/images/2016/09/05/1473094303380_29055bed9a.jpg","http://server7.upload69.net/images/2016/09/05/1473094303381_29056bcd4e.jpg","http://server7.upload69.net/images/2016/09/05/1473094303383_2905722ab9.jpg","http://server7.upload69.net/images/2016/09/05/1473094303386_2905963298.jpg","http://server7.upload69.net/images/2016/09/05/1473094303388_290608e13b.jpg"],"intro":"Gái gọi: Vân Du\nLoại hàng: gái gọi sài gòn\nNăm sinh:1993\nNguồn gốc: Miền Nam\nMã số: 0776\nGiá: 500k/ 1 Shot\nGiá nhà nghỉ, khách sạn: 70k/1H đầu.\nKhu vực thường xuyên hoạt động: Quận 10\nThời gian làm việc hàng ngày:10h-19h. Không qua đêm.\nSố điện thoại gái gọi: 01653870776 ,PASS: Bạn anh Thien Địa\n\n​LINK REPORT THAM KHẢO:\n\n(Tìm đầy đủ trên Google : Vân Du ms 0776 site : thiendia.com)\n\nhttp://thiendia.com/diendan/threads...ghia-phon-thuc-ngoan-ngoan-nhiet-inh.1032940/\n\nhttp://thiendia.com/diendan/threads/gai-goi-van-du-ms0776-hotgirl-acmn.1025470/\n\nhttp://thiendia.com/diendan/threads/van-du-ms0776-hotgirl-mien-tay-thanks-ttsh-q10.1011498/\n\nThông tin tham khảo theo tiêu chí Shot :\n\nDáng người : nhỏ nhắn , 1m58 , body khá đẹp , da mịn màng , trắng tươi .\n\nMặt : Xinh nhẹ nhàng , hay chuyện , thân thiện , cười duyên.\n\nNgực : ngực khá to , còn căng lắm , xài tốt , bú bóp vô tư\n\nEo : eo ót đâu ra đấy , không bèo nhèo , ít mỡ bụng\n\nMông : mông mãy và săn chắc , doggy rất êm .\n\nBướm : không calavat , sạch sẽ thơm tho lông lá tự nhiên um tùm .\n\nDịch vụ cam kết thực hiện : cuồng dâm đại pháp . liếm láp toàn thân , bj ,hj , đá bi, hợp tác mọi tư thế , vét máng thoải mái , nói chuyện vui , các kiểu dịch vụ .\n\nThời gian phục vụ : 1 shot 40 phút .\n\nKỹ thuật : cực chuyên nghiệp và điêu luyện , chiều khách .\n\nThái độ : lịch sự , nhẹ nhàng , ân cần , nói chuyện vui vẻ , không hối thúc - Không bỏ bom , không công nghiệp , không tráo hàng\n\ntakeshi0905 nói: ↑\nhttp://thiendia.com/diendan/threads/q3-q10-600k-hotnew-van-du-ms1921-hotgirl-tiem-toc.962183/\n\nhttp://thiendia.com/diendan/threads/gai-goi-van-du-ms0776-hotgirl-acmn.1025470/\n\nhttp://thiendia.com/diendan/threads/van-du-ms0776-hotgirl-mien-tay-thanks-ttsh-q10.1011498/\n\ncó thông tin em này từ khá lâu rồi , đến hôm nay lục lại tàng thư lại thấy , nóng hết người nên pahir bố trí phang .\n\nThông tin về hàng :\n\n- Nghệ danh :Vân Du\n- MS : 0776\n- năm sinh : 1993\n- Loại hàng : Gái gọi miên nam\n- Nguyên Quán : miền Nam\n- Khu vực hoạt động :Quận 10\n- Giá : 500k/1shot\n- Thời gian phục vụ : trung bình 40 phút / 1 shot\n- Thời gian làm việc : 11h trưa đến 22h00 tối .\n\n- Face : Xinh đẹp, chắc tầm 1m58, da trắng, mịn màng, mặt xinh.\n- V1 : 8đ vú em khá là to, nhưng đầu ti cũng đẹp, bóp khá thích\n- V2 : 7đ gọn gàng ít lipit.\n- V3 : 8đ cong, tròn lẵng, rất dễ bị thế doggy của em nó hạ gục\n- V4 : 9đ cắt tỉa cực đẹp, còn đẹp hồng hào, khít khao\n\nService : Em nó thuộc dạng khá dâm, khi bú mút cho mình còn đưa tay sờ bướm nữa cơ. Hôn ti, hôn đùi, hôn rốn, hôn thằng em, hôn bi ... Em có cũng cho tevet nhưng thường thích người sạch sẽ, nói chung Vân Du cũng khá nổi tiếng với anh em rồi  Giờ mình chỉ up lại cho em nó thôi.\n\nhình ảnh nào"},{"url":"http://thiendia.com/diendan/threads/lai-bi-dam-riet-chan-cai-nt.1033193/","title":"Lại bị đâm ! riết chán cái NT","unixTime":1473228441,"imgUrls":["http://imageshack.com/a/img922/4848/YJBoaB.png","http://imageshack.com/a/img923/8171/wTgqMI.jpg","http://imageshack.com/a/img923/9398/vo2y2q.jpg","http://imageshack.com/a/img924/317/nac4ub.jpg"],"intro":"3 chơi chó như vậy là cùng ! thôi đéo quen biết nên cũng đéo tức ! nhueng mà con trai đi tán gái mà lấy danh phận thằng khác đi bôi để kiếm cớ nói chiện vs gái là bó tay ! 1 lạy cho a ấy"},{"url":"http://thiendia.com/diendan/threads/gai-goi-quan-10-quyen-mt-ms-5032-nghe-thuat-tinh-duc-thang-hoa-full-service.1033192/","title":"Quận 10 - 500K - gái gọi quận 10 - Quyên MT - ms : 5032 - Nghệ thuật tình dục thăng hoa - FULL service","unixTime":1473228295,"imgUrls":["http://server7.upload69.net/images/2016/09/03/1472876563939_264708f61e.jpg","http://server7.upload69.net/images/2016/09/03/1472876567754_2647104d4f.jpg","http://server7.upload69.net/images/2016/09/03/1472876571159_26472456af.jpg","http://server7.upload69.net/images/2016/09/03/1472876575546_2647341541.jpg","http://server7.upload69.net/images/2016/09/03/1472876578567_264747ad65.jpg","http://server7.upload69.net/images/2016/09/03/1472876581657_26475e25c1.jpg","http://server7.upload69.net/images/2016/09/03/1472876584771_264765c92f.jpg","http://server7.upload69.net/images/2016/09/03/1472876587965_264778f01e.jpg","http://server7.upload69.net/images/2016/09/03/1472876592172_26478c9540.jpg","http://server7.upload69.net/images/2016/09/03/1472876596416_264797dc02.jpg","http://server7.upload69.net/images/2016/09/03/1472876600411_26480ec7a0.jpg","http://server7.upload69.net/images/2016/09/03/1472876604198_26481331e3.jpg","http://server7.upload69.net/images/2016/09/03/1472876608257_264829e1c1.jpg","http://server7.upload69.net/images/2016/09/03/1472876612882_264832395b.jpg"],"intro":"Gái gọi: Quyên MT\nLoại hàng: gái gọi sài gòn\nNăm sinh:1992\nNguồn gốc: Miền Nam\nMã số: 5032\nGiá: 500k/ 1 Shot\nGiá nhà nghỉ, khách sạn: 70k/1H đầu.\nKhu vực thường xuyên hoạt động: Quận 10\nThời gian làm việc hàng ngày:10h-19h. Không qua đêm.\nSố điện thoại gái gọi: 0902655032 ,PASS: Bạn anh Thien Địa\n\n​LINK REPORT THAM KHẢO:\n(Tìm đầy đủ trên Google : Quyên MT ms 5032 site : thiendia.com)\n\nhttp://thiendia.com/diendan/threads...huat-tinh-duc-thang-hoa-full-service.1032376/\n\nThông tin tham khảo theo tiêu chí Shot :\n\nDáng người : nhỏ nhắn , 1m57 , body khá đẹp , da mịn màng , trắng tươi .\n\nMặt : Xinh nhẹ nhàng , hay chuyện , thân thiện , cười duyên.\n\nNgực : ngực vừa tay , đầu ti tụt , còn căng lắm , hàng xịn , xài tốt , bú bóp vô tư\n\nEo : eo ót đâu ra đấy , không bèo nhèo , ít mỡ bụng\n\nMông : mông mãy và săn chắc , doggy rất êm .\n\nBướm : không calavat , sạch sẽ thơm tho lông lá tự nhiên um tùm .\n\nDịch vụ cam kết thực hiện : cuồng dâm đại pháp . liếm láp toàn thân , bj ,hj , đá bi, hợp tác mọi tư thế , vét máng thoải mái , nói chuyện vui , service chuyên nghiệp , các kiểu dịch vụ .\n\nThời gian phục vụ : 1 shot 60 phút .\n\nKỹ thuật : cực chuyên nghiệp và điêu luyện , chiều khách .\n\nThái độ : lịch sự , nhẹ nhàng , ân cần , nói chuyện vui vẻ , không hối thúc - Không bỏ bom , không công nghiệp , không tráo hàng\n\nblue wolf nói: ↑\nvốn là khách quen của em Quyên MT ms 5032 rất nhiều lần rồi có thể nói là nghiện\n\n_ nghiện từ tiếng alo set kèo cực gợi tình\n_ nghiện từ mùi hương trên tóc e khi vừa bước vào phòng đã ôm hôn\n_ nghiện đến ánh mắt dâm dục gợi tình khi e kéo lưng quần lôi mình vào tắm cùng\n_ nghiện cho đến hệ thống ngôn từ khẩu dâm vô cùng phong phú đến cháy bỏng người nghe\n_ đang mân mê thoa xà phòng cho nhau khiến mình chào cờ đến nóng rang cả người thì bất ngờ e mở nước xả sạch người mình với 1 lý do vô cùng chính đáng :\n\" e chịu hết nổi rồi a ơi \" ............ xả xong ngồi xuống BJ tại WC khiến mình ko kịp trở tay\nĐc BJ ngất ngây với dỗ éo lưỡi cực bót và áp suất cực cao khiến mình đã ngất ngây con gà tây rồi đã thế còn đang đứng dưới vòi sen tê tái nữa ............ 1 khung cảnh , 1 cảm giác cứ như \"thiên thượng nhân gian\"\nCái câu thiên thượng nhân gian quả ko sai tý nào vì thần tiên chưa chắc đã có dc cảm xúc như mình lúc này và ko chỉ dừng lại ở như thế\nCả 2 đã ôm chầm quấn quít nhau cháo lưỡi dần dần cho đến khi lên giường và e khẽ hỏi nhỏ nhẹ vào tai mình \" a muốn e phục vụ kiểu Mỹ hay kiểu nhật nè \" ....... ôi lạy hồn \"chinsu\"\nEm mạnh dạn và tự hào show bộ nghệ thuật làm tình siêu bá đạo của e với 10 tư thế BJ thần thánh khiến mình suýt out mấy lần và sau màn BJ thứ 7 đó là 69 úp và ngửa mình đã đầu hàng xin phép em ấy dc chiến cho cuộc vui dc trọn vẹn hehe\nKhi vào chiến thì mình càng ngạc nhiên hơn khi thấy dc thêm 1 nét đẹp trong nghệ thuật làm tình của e ấy đó là :\n_ cảm xúc biểu lộ qua ánh mắt dâm đãng gợi tình khi cậu nhỏ từ từ tiến vào cho đến khi lút cán thì ánh mắt ấy nhắm tít lại và miệng phát ra 1 âm thanh thỏa mãn đến tột cùng của e ấy\n\n_ ngoài ra trong khi chiến e ấy liên tục phát ngôn khẩu dâm 1 cách mỹ miều chứ ko thô tục nhưng tiếng nói trong trẻo dâm đãng ấy cứ bị nất lên theo nhịp nhấp và rên rỉ đến rúng động những phòng xung quanh ......ôiiiiiiiiiiiiii\n\nSau 4 hay 5 tư thế gì đó mình đã quay lại tư thế truyền thống cả 2 đã ôm ghì chặt lấy nhau và nhấp theo nhịp rất đều và rất sâu từ nghĩa đen đến nghĩa bóng dc tầm 10 nhịp bỗng e ấy run run người lên và bắt đầu co giật âm đạo OMG e ấy đã CUM ướt cả đệm cảm giác vô cùng yomost\n\nTuy dâm nhưng e ko quên nghề của e là chăm sóc checker khi e ấy mình ra mồ hôi nhiều quá nên e đã nhẹ nhàng gợi ý \" để e phục vụ BJ cho a đến CIA luôn a chiệu ko nè cục cưng , chứ e thấy a mệt e thương quá à \" .................. ôi tuyệt còn gì bằng CIA nữa chứ hahaha\n\n* * * ko còn gì để diễn tả cảm giác ngon chim đến bá đạo ntn ( ko nghiện mới lạ )\n\n- Nghệ danh : Gái gọi Quyên MT\n- Mã số : 9489\n- Loại hàng : Gái gọi Gài Gòn\n- Giá : 400k/s\n- KV hoạt động : Lê Hồng Phong - Q10\n- Nguồn gốc : Miền Nam\n- Tuổi : Tầm 1992\n- giá : 500k / Shot\n- Giá Ks : 80k > 120k ( tùy loại phòng )\n- thời gian phục vụ : Em này đi theo tiếng , nên các bác cứ bấm thời gian đủ một tiếng nhé\n- Thời gian làm việc : 9h sáng đến 19h tối\n- Face : Tầm 7d, nhìn khá xinh\n- Body : Hơi nhỏ con, nhỏ nhỏ xinh xinh bác nào khỏe ẳm lên chịch đc đó\n- V1 : hệ Cam bóp quá đã , hàng thật nhé\n- V2 : có 1 tí xíu mỡ thôi\n- V3 : săn chắc, nhìn ngon lành doggy tốt\n- V4 : Bím còn đẹp lắm nha bà con, vét máng vô tư luôn cho bác nào thích\n- Service : Các bác thích phục vụ theo tiêu chuẩn nào . Nhật Bản , Châu Âu hay Châu Mỹ , em nó chiều hết nha .\nTóm lại là bác nào thích phục vụ kiểu hưởng thụ , nằm ôm , tâm sự , chịch thoải mái thời gian là bét nhè , thì cứ alo và nhích thôi .\n\nHình ảnh thôi nào !"},{"url":"http://thiendia.com/diendan/threads/my-uyen-9101-gai-can-tho-nhiet-tinh-va-ngoan-ngoan.991731/","title":"TDH-NTĐ - 300K - Mỹ Uyên 9101 - Gái cần thơ nhiệt tình và ngoan ngoãn","unixTime":1458950400,"imgUrls":["http://img.thiendia.com/server7/images/2015/10/06/IMG_1824991c9.jpg","http://img.thiendia.com/server7/images/2015/10/06/IMG_18253f513.jpg","http://img.thiendia.com/server7/images/2015/10/06/IMG_18260dbf1.jpg","http://img.thiendia.com/server7/images/2015/10/06/IMG_1827101d6.jpg","http://img.thiendia.com/server7/images/2015/10/06/IMG_1828ab26a.jpg","http://img.thiendia.com/server7/images/2015/10/06/IMG_182946acd.jpg","http://img.thiendia.com/server7/images/2015/10/06/IMG_1830aef70.jpg","http://img.thiendia.com/server7/images/2015/10/06/IMG_1831d10ef.jpg","http://img.thiendia.com/server7/images/2015/10/06/IMG_1832180ae.jpg","http://img.thiendia.com/server7/images/2015/10/06/IMG_1833efe0e.jpg","http://img.thiendia.com/server7/images/2015/10/06/IMG_183473ebc.jpg","http://img.thiendia.com/server7/images/2015/10/06/IMG_183577973.jpg","http://img.thiendia.com/server7/images/2015/10/06/IMG_18365a0ef.jpg","http://img.thiendia.com/server7/images/2015/10/09/IMG_189815205.jpg","http://img.thiendia.com/server7/images/2015/10/09/IMG_1899b6c6f.jpg","http://img.thiendia.com/server7/images/2015/10/09/IMG_190251916.jpg","http://img.thiendia.com/server7/images/2015/10/09/IMG_1903a62f0.jpg","http://img.thiendia.com/server7/images/2015/10/09/IMG_1895f76fc.jpg","http://img.thiendia.com/server7/images/2016/02/26/1902a8.jpg","http://img.thiendia.com/server7/images/2016/02/26/398062.jpg","http://img.thiendia.com/server7/images/2016/02/26/4efab3.jpg"],"intro":"Nghệ danh: Mỹ Uyên\n\nMã số: 9101\n\nGiá: 300k /Shot\n\nGiá nhà nghỉ, khách sạn: 100k /2H.\n\nThời gian phục vụ 35p\n\nKhu vực thường xuyên hoạt động: Trần Duy Hưng, Nguyễn Ngọc Vũ\n\n[hide]SỐ ĐIỆN THOẠI: 0989979101 PASS: lấy số ở thiên địa[/hide]\n\nLINK REPORT THAM KHẢO:\n(Tìm đầy đủ trên Google: TÊN HÀNG + MÃ SỐ site:thiendia.com)\nhttp://thiendia.com/diendan/showthread.php?t=966167\nhttp://thiendia.com/diendan/showthread.php?t=966580\n\nTHÔNG TIN THAM KHẢO: (theo tiêu chí giá /shot)\n\nDáng ngườiong dỏng, da nâu, dáng đẹp\n\nPhong cách: Duyên,ăn nói nhẹ nhàng đáng yêu (7đ)\n\nMặt: Khuôn mặt khá thiện cảm (7đ)\n\nNgực: To, chắc, do da nâu nên đầu ti hơi thâm (7đ)\n\nEo: hợp với dáng, lipit rất ít (7đ)\n\nMông: Cong, úp thìa cũng rất mềm mại êm ái (7đ)\n\nBướm: Ca vát cũng có, điện nước đầy đủ, bướm khít nên co bóp rất tốt (7đ)\n\nDịch vụ: BJ, HJ\n\nKỹ thuật, secvit: Khá tốt\n\nDịch vụ cam kết thực hiện: Liếm láp toàn thân, với màn Bj điêu luyện mút mát phê lòi, một tay giữ chim lưỡi đá lên đá xuống, đầu gật như bổ củi làm mình tí out các b cứ đi rồi cảm nhận. Hôn môi chắc chắn có, vét máng thì e chưa thử nên hông dám chắc.\n\nThái độ: Rất ngoan ngoãn, Không công nghiệp\n\nChú ý:\n\n- Thể hiện văn hóa checker LX khi check hàng.\n\n- Đề nghị khi check hàng không: Sử dụng ma túy, say rượu bia, dọa nạt hoặc có những đòi hỏi quá đáng đối với hàng.\n\n- Checker khi check về nhớ có report, phản ánh để bổ sung thêm thông tin.\n\n​"},{"url":"http://thiendia.com/diendan/threads/gai-goi-quan-phu-nhuan-ngoc-0741-net-dep-den-tu-nhat-ban.986079/","title":"Máy Bay - Phú Nhuận - 300K - gái gọi quận phú nhuận Ngọc 0741 - Nét đẹp đến từ Nhật Bản","unixTime":1456099200,"imgUrls":["https://s31.postimg.org/dfzxrzamz/sketch_1469695963847.png","https://s31.postimg.org/lmwixaq3f/sketch_1469696038453.png","https://s31.postimg.org/p7segiumz/sketch_1469696267091.png","https://s31.postimg.org/8lau7g1p7/sketch_1469696318777.png","https://s31.postimg.org/ciy3wuoij/sketch_1469696660117.png","https://s31.postimg.org/g3tzg2t23/sketch_1469707563415.png","https://s31.postimg.org/5v1ia950b/sketch_1469707601155.png","https://s31.postimg.org/qt7o8c4uz/sketch_1469707640873.png","https://s31.postimg.org/u1c5ldr4r/sketch_1469707715245.png","https://s31.postimg.org/q68rit7yz/sketch_1469707757640.png","http://s33.postimg.org/x2nsrc7nz/image.jpg","http://s33.postimg.org/8v37msjpr/image.jpg","http://s33.postimg.org/4ah17v00f/image.jpg","http://s33.postimg.org/x1duxx5u7/image.jpg","http://s33.postimg.org/w47fp1ubz/image.jpg","http://s33.postimg.org/sut0il68f/image.jpg","http://s33.postimg.org/urpqn5wwf/image.jpg","http://s33.postimg.org/n090olsr3/image.jpg","http://s33.postimg.org/csv2pxvwv/image.jpg","http://img.thiendia.com/server7/images/2016/01/26/b6c826bc54b194415e72f75ccdaf6d2b.jpg"],"intro":"Gái gọi: Ngọc\nLoại hàng: máy bay thương mại sài gòn\nNăm sinh: 1989\nNguồn gốc: Miền Bắc\nMã số: 0741\nGiá: 300k/ 1 Shot\nGiá nhà nghỉ, khách sạn: 80k/2H đầu.\nKhu vực thường xuyên hoạt động: Tân Bình\nThời gian làm việc hàng ngày: Phục vụ từ 10h đến 23h. Không qua đêm\nSố điện thoại gái gọi: 01227300741 PASS: lấy số ở thiendia​\n\nLINK REPORT THAM KHẢO:\nhttp://thiendia.com/diendan/showthread.php?t=984968\n\nTHÔNG TIN THAM KHẢO: (theo tiêu chí giá /shot)\n\nDáng người: mảnh khảnh, thon gọn\n\nMặt: (7.5đ)đúng nét đẹp mặn mà\n\nNgực: ( 5đ) hệ cam, nhưng bù lại, bú liếm vô tư\n\nEo: ( 8đ) thon gọn, bằng tiêu chuẩn con gái\n\nMông: ( 7đ) căng đét, doggy chuẩn\n\nBướm: ( 6đ) khá ngon, gọn gàng sạch sẽ\n\nDịch vụ cam kết thực hiện: (Dịch vụ không cam kết nghĩa là không bắt buộc hàng phải phục vụ)\nBj: có\nHj: có\nBú liếm hôn hít: Có\nHôn môi:không\nChơi some: Không\nLỗ nhị: Không\nQua đêm: Không\n\nThời gian phục vụ (tính từ lúc bắt đầu làm tình, không tính thời gian cởi quần áo) 45 phút/shot\n\nKỹ thuật: Đỉnh của Tỉnh! BJ nhẹ nhàng, kích thích, Ai yếu là out từ vòng gửi xe, Ai mạnh out từ vòng xét tuyển! Cảm giác làm tình thật như người tình!\nThái độ: vui vẻ, lễ phép, đúng giờ giấc, hay cười\n\nnottram nói: ↑\nSài Gòn đã vào mùa mưa. Dù là cơn mưa ầm ào bất chợt đổ xuống, hay rả rích từ chiều đến đêm thì cũng đều mang đến cho người ta nhiều cảm xúc lẫn lộn. Đôi khi đó là sự ngao ngán phải đội mưa đi về. Là sự khắc khoải khi lẻ loi trên phố. Là cảm giác cô đơn trào dâng. Và cũng là lúc mà làm cho bản năng, khao khát yêu thương, dục vọng của Con người trỗi dậy.\n\nVà… Tôi cũng không là ngoại lệ. Liền nghĩ đến Em sau hơn 1 tháng xa cách, với tay lấy chiếc điện thoại, tôi gọi cho Em\n\nTôi: Alo. Em à?\nNgọc 0741: Vâng Em đây\nTôi: Em đã vào SG chưa?\nNgọc 0741: Em vừa vào hôm qua, Em nói với A rồi mà!\nTôi: hê hê! À ừ, A quên, thế bây giờ Em rảnh không Anh qua?\nNgọc 0741: Với Anh thì lúc nào chẳng rảnh, A qua đi\n\nĐúng là, đến khi mất đi một điều gì đó, thì bản thân Mình mới nhận ra được điều đó quan trọng với bản thân ntn. Thời gian mà Em rời xa chốn Thành Phố, là khoảng thời gian mà Tôi chẳng thể tìm thấy được sự thăng hoa, khoái cảm mà Em đã đem lại, dù đã quan hệ với nhiều người.\n\nMở cửa ra, Tôi chỉ có thể thốt lên 1 câu “DKM !!!”\n\nEm vẫn là Em, nhưng Em đẹp hơn lúc trước rất nhiều. Mái tóc mang đậm phong cách của những Japan Angels kết hợp với bộ váy làm Em trở nên thật lộng lẫy. Bản năng thôi thúc, không kịp hỏi thăm Em. Tôi khóa cửa và bắt đầu làm theo cảm xúc của Mình.\n\nCơ hội đã tới, tay tôi xoa nhẹ lên xuống cánh tay em. Tôi nghe em thở gấp … cả hai tay tôi ghì chặt vòng eo thon thả của em, rồi vuốt ve nhẹ nhàng vùng bụng, rồi lần xuống đôi đùi thon thả … hai tay em giữ hai tay tôi nửa như muốn ngăn tôi, nửa như muốn khuyến khích tôi tiếp tục …\n\nTrời tối và lạnh càng làm cho cả hai chúng tôi hứng khởi hơn, quấn quít nhau hơn … Hai tay tôi rời vùng bụng của em để tiến sâu xuống phía dưới … Chim tôi cương cứng tự hồi nào đang thoi thóp thúc vào mông em … Em càng dựa sát hơn vào người tôi … Tôi nghe rõ nhịp thở gấp của em … Tôi mạnh dạn dùng lưỡi liếm lên tai, rồi má, rồi cổ em … Hai tay tôi nhanh chóng tiến sâu xuống vuốt mạnh hai đùi em … rối bất ngờ cả hai tay tôi cùng một lúc ào tiến vào háng của em … Em thở gấp … rồi rên khẻ … rồi rên lớn dần … Qua hai lớp vải mỏng, tôi vẫn cảm nhận được âm hộ em thật ấm, căng cứng như muốn nổ tung … tôi vuốt nhẹ … rồi hẩy âm hộ em lên … rồi vuốt nhẹ … ngón tay tôi lướt nhẹ đi tìm “khe suối vàng”\n\nEm rên càng lúc càng to hơn, rõ hơn … Thân hình em nhúch nhích làm cho mông em cọ sát làm cho chim tôi càng lúc càng cương cứng hơn … bất ngờ, em cho tay ra sau và mò xuống nắm lấy chim tôi, rồi bóp nhẹ … tôi nhắm mắt tận hưởng … em vuốt lên rồi vuốt xuống làm chim tôi như muốn nổ tung … hai tay tôi nhanh nhẹn lòn qua chiếc váy của em … làn da em mát lạnh … em rên to hơn … quần xì mỏng của em ướt sũng … hai tay tôi mân mê từng thớ thịt âm đạo của em … rồi tôi dùng cả bàn tay để vuốt nhẹ toàn bộ âm đạo em … hai tay em vẫn không ngừng nắn bóp chim tôi … em bóp càng lúc càng mạnh hơn …\n\nNgọc 0741: Anh ơi… A cho vào đi…\nTôi: uh, Em đeo vào cho Anh nhé!\nNgọc 0741: Vâng\nNgọc 0741: nhẹ thôi Anh nha\nTôi: uh\nNgọc 0741: ah… ôi Anh ơi Em sướng quá\n\nCứ thế 15p trôi qua. Tôi vỡ òa trong sự sung sướng. Xin cảm ơn Em, người con gái tuyệt vời\n\nMBTM Ngọc 0741 - Trung Tâm Share Hàng - TB - 300k\nFace: xinh, da trắng, mịn, răng đều đẹp\nV1,V2,V3,V4 A/e tự đánh giá nhé!\nMọi thông tin đều ở trong TTSH, A/e Đừng Inbox Mình"},{"url":"http://thiendia.com/diendan/threads/trung-kinh-phuong-ly-ms-9856-moi-cong-goi-cam.953387/","title":"TDH-NTĐ - 250K - [TRUNG KÍNH] PHƯƠNG LY Ms: 9856 - Môi cong gợi cảm","unixTime":1441238400,"imgUrls":["http://img.thiendia.com/server6/images/87902609184576841532.jpg","http://img.thiendia.com/server6/images/78663131333437987406.jpg","http://img.thiendia.com/server6/images/24282446938396709949.jpg","http://img.thiendia.com/server6/images/51924640439995543614.jpg","http://img.thiendia.com/server6/images/72163438482299355660.jpg","http://img.thiendia.com/server6/images/59318446069466480793.jpg","http://img.thiendia.com/server6/images/56471606409102305817.jpg","http://img.thiendia.com/server6/images/20826716601950542361.jpg","http://img.thiendia.com/server6/images/41526017844130813984.jpg"],"intro":"Nghệ danh: PHƯƠNG LY\n\nMã số: 9856\n\nGiá: 250k /Shot\n\nGiá nhà nghỉ, khách sạn: 100k /2H đầu.\n\nKhu vực thường xuyên hoạt động: Trung kính\n\nSỐ ĐIỆN THOẠI 0919.209.856 PASS: Thiên địa hội\n\nLINK REPORT THAM KHẢO:\n(Tìm đầy đủ trên Google: Tên + Mã số site:thiendia.com)\n\nTHÔNG TIN THAM KHẢO: (theo tiêu chí giá /shot)\n\nDáng người: Cao khoảng 1m6\n\nMặt: Ưa nhìn, có nét xinh, đôi môi khá gợi cảm - 7\n\nNgực: Hệ cam, hơi mềm. Nếu ngực không yếu có lẽ em không đi giá này - 6 -\n\nEo: Trung bình, có mỡ thừa - 6\n\nMông: Khá căng, doggy ổn -7\n\nBướm: lông lá tự nhiên ko rậm rạp, cũng khít , nước nôi bình thường - 7\n\nDịch vụ cam kết: BJ, HJ.\n\nDịch vụ khác: Không\n\nKỹ thuật, secvit: Khá\n\nThái độ: Nhẹ nhàng, Không giục giã (Trừ trường hợp khách hàng sử dụng ma túy, thuốc kích dục, quá say xỉn, bạo dâm hoặc đòi hỏi quá đáng)\n\nChú ý:\n- Đọc kỹ thông tin trước khi check.\n\n- Thể hiện văn hóa checker LX khi check hàng. Khi check hàng không: Sử dụng ma túy, thuốc kích dục, quá say xỉn, dọa nạt hoặc có những đòi hỏi quá đáng đối với hàng.\n\n- Checker khi check về nhớ có report, phản ánh.\n\n​"}]