[ {
  "url" : "https://thiendia.com/diendan/threads/tam-nghi-tu-trinh-2594-6206-cuc-pham-trong-tam-gia-non-ngon-ngot-thom.1211366/",
  "title" : "400K - Quận 1 - [TẠM NGHỈ] Tú Trinh 2594 (6206) - cực phẩm trong tầm giá , non , ngon , ngọt , thơm",
  "unixTime" : 1550667600,
  "imgUrls" : [ "https://greenupload.com/images/2019/01/21/3e803ad88333606d3922.jpg", "https://greenupload.com/images/2019/01/21/8b9d30c0892b6a75333a.jpg", "https://greenupload.com/images/2019/01/21/13b2626cdb8738d96196.jpg", "https://greenupload.com/images/2019/01/21/232d16ffaf144c4a1505.jpg", "https://greenupload.com/images/2019/01/21/3105c067798c9ad2c39d.jpg", "https://greenupload.com/images/2019/01/21/05811e54a7bf44e11dae.jpg", "https://greenupload.com/images/2019/01/21/509006c3bf285c760539.jpg", "https://greenupload.com/images/2019/01/21/5177202986c2659c3cd3.jpg", "https://greenupload.com/images/2019/01/21/ab78f92a5fc1bc9fe5d0.jpg", "https://greenupload.com/images/2019/01/21/bfac19f6a01d43431a0c.jpg", "https://greenupload.com/images/2019/01/21/dd357869de823ddc6493.jpg", "https://greenupload.com/images/2019/01/21/e373e21e5bf5b8abe1e4.jpg", "https://greenupload.com/images/2019/01/21/eb76dbaa6241811fd850.jpg", "https://greenupload.com/images/2019/01/21/f8ff4aaff344101a4955.jpg", "https://greenupload.com/images/2019/01/21/f754ec84556fb631ef7e.jpg" ],
  "intro" : "Gái gọi Tú Trinh 2549\n400k/shot\n\nGái gọi Sài Gòn\nNhà nghỉ80k/h\nQuận 1\nlấy số ở Thiendia\n1997\nXuất xứmiền TÂY\nCaovừa vặn , không mập , không ốm , mông vú nẩy nở, skin trắng mịn mát lạnh thơm phức, cao 1.60m\nDaTrắng vừa , mịn màng\nMặt\nhiền lành nhìn dễ thương, xinh xắn nữ tính, đậm nét thiếu nữ nam bộ pha chút dâm tà khi cười, mà em cười suốt\n\nhệ cam , ti bé bé hồng hồng , săn tròn mềm ko nhão\nEo\nBÉ tí tẹo teo , phẳng mượt như tập GYM\n\nQuả mông tròn căng , mịn màng\nBímSiêu phẩm bím\nnước đủ xài, bót vkl, bên trong còn hồng hào, cắt tỉa gọn gàng, sạch sẽ, tevez sướng thôi rồi\nServiceKis môi\nHôn vú, bóp vú\nHJ, BJ\nVét máng\n\n30-40 phút / lần phọt\n9h - 23h hàng ngày\nĐánh_giá em này phải nói cực ngon, và thái độ làm việc hết sức nhiệt tình, ngoan ngoãn gọi dạ bảo vâng .\nLINK REPORT THAM KHẢO:\n\nhttps://www.thiendia.com/diendan/th...oder-nho-be-minh-ket-em-nay-den-chet.1020131/"
}, {
  "url" : "https://thiendia.com/diendan/threads/tam-nghi-linh-anh-7983-hang-cuc-ngon-trong-tam-gia-moi-nhap-khau.1210245/",
  "title" : "250K - Máy Bay - Quận 10 - [TẠM NGHỈ] Linh Anh 7983 - Hàng cực ngon trong tầm giá , mới nhập khẩu",
  "unixTime" : 1549976400,
  "imgUrls" : [ "https://greenupload.com/images/2019/01/12/_MG_6293.jpg", "https://greenupload.com/images/2019/01/12/_MG_6295.jpg", "https://greenupload.com/images/2019/01/12/_MG_6296.jpg", "https://greenupload.com/images/2019/01/12/_MG_6300.jpg", "https://greenupload.com/images/2019/01/12/_MG_6302.jpg", "https://greenupload.com/images/2019/01/12/_MG_6304.jpg", "https://greenupload.com/images/2019/01/12/_MG_6306.jpg", "https://greenupload.com/images/2019/01/12/_MG_6308.jpg", "https://greenupload.com/images/2019/01/12/_MG_6312.jpg", "https://greenupload.com/images/2019/01/12/_MG_6314.jpg", "https://greenupload.com/images/2019/01/12/_MG_6316.jpg", "https://greenupload.com/images/2019/01/12/_MG_6318.jpg", "https://greenupload.com/images/2019/01/12/_MG_6322.jpg" ],
  "intro" : "Gái gọi Linh Anh 7983\n250K/shot\nMBTM Sài gòn\n\nNhà nghỉ60k-80k/h\nSư vạn hạnh - quận 10\nlấy số ở Thiendia\n1988\nXuất xứMiền Băc\nCao160 cm\nDaDa trắng\nMặtMặt xinh dâm\nto vừa tay\nEohơi tròn\nTròn căng đét, to\nBímkhông calavat , bót chặt\nServicehôn môi\nhôn vú\nHJ , BJ\nVét máng\nbóp thoải mái\n\n30-40 phút / lần phọt\n11h-23h hàng ngày\nĐánh_giá_chungquá đẹp với giá 250k . nhiệt tình , nhẹ nhàng , vui vẻ , không công nghiệp . đảm bảo rất thích luôn nhé .\nLINK REPORT THAM KHẢO:\n\nhttps://thiendia.com/diendan/thread...cuc-ngon-trong-tam-gia-moi-nhap-khau.1210101/"
}, {
  "url" : "https://thiendia.com/diendan/threads/tam-nghi-my-duyen-0379-em-gai-than-hinh-nong-bong-cuc-dam-dang.1210248/",
  "title" : "400K - Trung Sơn-Q.8 - [TẠM NGHỈ] Mỹ Duyên 0379 - EM GÁI THÂN HÌNH NÓNG BỎNG CỰC DÂM ĐÃNG",
  "unixTime" : 1549976400,
  "imgUrls" : [ "https://greenupload.com/images/2019/01/12/3b41682a28dccb8292cd.jpg", "https://greenupload.com/images/2019/01/12/6f6d2f066ff08caed5e1.jpg", "https://greenupload.com/images/2019/01/12/7e43222862de8180d8cf.jpg", "https://greenupload.com/images/2019/01/12/8ee1e28aa27c4122186d.jpg", "https://greenupload.com/images/2019/01/12/224e742534d3d78d8ec2.jpg", "https://greenupload.com/images/2019/01/12/258c6be72b11c84f9100.jpg", "https://greenupload.com/images/2019/01/12/640b72603296d1c88887.jpg", "https://greenupload.com/images/2019/01/12/9042a429e4df07815ece.jpg", "https://greenupload.com/images/2019/01/12/15590c324cc4af9af6d5.jpg", "https://greenupload.com/images/2019/01/12/589566fe2608c5569c19.jpg", "https://greenupload.com/images/2019/01/12/7647662c26dac5849ccb.jpg", "https://greenupload.com/images/2019/01/12/b701dd6a9d9c7ec2278d.jpg", "https://greenupload.com/images/2019/01/12/d904be6ffe991dc74488.jpg", "https://greenupload.com/images/2019/01/12/ddd8adb3ed450e1b5754.jpg", "https://greenupload.com/images/2019/01/12/e527c94c89ba6ae433ab.jpg" ],
  "intro" : "Gái gọi Mỹ Duyên 0379\n400K/shot\nGái gọi Sài Gòn\n\nNhà nghỉ80K/h\nTRUNG SƠN - QUẬN 8\nlấy số ở Thiendia\n1997\nXuất xứTây Bắc\nCao160cm\nDaTrắng nhẹ\nMặtxinh xắn dễ thương , duyên, đáng yêu, lúc nào cũng cười tươi ko cần tưới, cao 1.60m chưa guốc\nhệ cam, cam kết hàng thật, săn chắc tay, bú bóp thoải mái\n\nEo eo ót vừa dáng , tròn tròn , ôm đã\nto tròn vểnh , đẹp, doggy tê tái\nBímđẹp, lông tự nhiên, múp , ngọt nước, bao nước nhé\nService Hôn môi (tuỳ khách, có thể ko có)\nHôn vú, Bóp vú\nHj, Bj\nVét máng\n\n30-40 phút / lần phọt\n10h - 24h hàng ngày\nĐánh giáem phục vụ tuyệt vời và cực kỳ yêu nghề vì em cần công việc, khác biệt rất nhiều so với nhiều em khác, anh em đi hướng dẫn thêm em luôn ngoan ngoãn tiếp thu LINK REPORT THAM KHẢO:\n\nhttps://thiendia.com/diendan/thread...bac-than-hinh-nong-bong-cuc-dam-dang.1210105/"
}, {
  "url" : "https://thiendia.com/diendan/threads/tam-nghi-bao-nhu-6273-lung-linh-voi-em-gai-mien-nam-chich-gap-anh-em-oi.1209970/",
  "title" : "300K - Quận 10 - [TẠM NGHỈ] Bảo Như 6273 - Lung linh với em gái miền NAM , chịch gấp anh em ơi .",
  "unixTime" : 1549803600,
  "imgUrls" : [ "https://greenupload.com/images/2019/01/11/1fdaae3242d8a186f8c9.jpg", "https://greenupload.com/images/2019/01/11/4bb8ab5347b9a4e7fda8.jpg", "https://greenupload.com/images/2019/01/11/8d49f7a21b48f816a159.jpg", "https://greenupload.com/images/2019/01/11/9f995f73b39950c70988.jpg", "https://greenupload.com/images/2019/01/11/39c8c52329c9ca9793d8.jpg", "https://greenupload.com/images/2019/01/11/60ddda2836c2d59c8cd3.jpg", "https://greenupload.com/images/2019/01/11/83f7201fccf52fab76e4.jpg", "https://greenupload.com/images/2019/01/11/579c4f77a39d40c3198c.jpg", "https://greenupload.com/images/2019/01/11/5868d2833e69dd378478.jpg", "https://greenupload.com/images/2019/01/11/94044fefa305405b1914.jpg", "https://greenupload.com/images/2019/01/11/ac4181b46d5e8e00d74f.jpg", "https://greenupload.com/images/2019/01/11/b6e980036ce98fb7d6f8.jpg", "https://greenupload.com/images/2019/01/11/bc8aee60028ae1d4b89b.jpg", "https://greenupload.com/images/2019/01/11/c3df942a78c09b9ec2d1.jpg", "https://greenupload.com/images/2019/01/11/c9245cd1b03b53650a2a.jpg" ],
  "intro" : "Gái gọi Bảo Như 6273\n300k/shot\nGái gọi Sài Gòn\n\nNhà nghỉ80K-100/h\nQUẬN 10\nlấy số ở Thiendia\n1991\nXuất xứMiền Nam\nCao160cm\nDatrắng nhẹ mịn màng\nMặtKhá xinh và duyên. E để mặt mộc mạc nhìn rất phê\nđẹp tự nhiên , bú bóp thoải mái\nEođẹp phẳng , mịn màng\nquả mông to tròn, cong mãy, vừa ôm eo vừa doggy rât tuyệt\nBímĐẹp . Bím em sạch sẽ, lông lá tự nhiên, còn rất khít và co bóp tốt. Bím rất thơm tho và nhiều nước, bao vét\nService Hôn môi\nVét máng\nHôn vú, bóp vú\nHJ, BJ\nBú bóp thoải mái\n\n30-40 phút / lần phọt\n9h - 21h hàng ngày\nĐánh_giángoan hiền, nói chuyện vui vẻ, không hối thúc, gái miền Nam chuẩn 100%, làm vì cuộc sống cam kết yêu nghề\nLINK REPORT THAM KHẢO:\n\nhttps://thiendia.com/diendan/thread...-em-gai-mien-nam-chich-gap-anh-em-oi.1209968/"
}, {
  "url" : "https://thiendia.com/diendan/threads/tam-nghi-co-giao-thao-2501-co-giao-mien-tay-thac-sy-bu-liem-len-sai-thanh.1209288/",
  "title" : "250K - Máy Bay - Quận 10 - [TẠM NGHỈ] Cô giáo Thảo 2501 - cô giáo miền tây, Thạc sỹ bú liếm , lên sài thành",
  "unixTime" : 1549458000,
  "imgUrls" : [ "https://greenupload.com/images/2019/01/07/0d3c640ffcc81f9646d9.jpg", "https://greenupload.com/images/2019/01/07/3fea2fd9b71e54400d0f.jpg", "https://greenupload.com/images/2019/01/07/07ccbfff2738c4669d29.jpg", "https://greenupload.com/images/2019/01/07/7a512362bba558fb01b4.jpg", "https://greenupload.com/images/2019/01/07/32d32ce0b42757790e36.jpg", "https://greenupload.com/images/2019/01/07/060a7239eafe09a050ef.jpg", "https://greenupload.com/images/2019/01/07/772d7d1ee5d906875fc8.jpg", "https://greenupload.com/images/2019/01/07/779fc7ac5f6bbc35e57a.jpg", "https://greenupload.com/images/2019/01/07/518997bb0f7cec22b56d.jpg", "https://greenupload.com/images/2019/01/07/5339820b1accf992a0dd.jpg", "https://greenupload.com/images/2019/01/07/70454576ddb13eef67a0.jpg", "https://greenupload.com/images/2019/01/07/c154e86770a093fecab1.jpg", "https://greenupload.com/images/2019/01/07/c3371a0582c2619c38d3.jpg", "https://greenupload.com/images/2019/01/07/d9239d1005d7e689bfc6.jpg", "https://greenupload.com/images/2019/01/07/dd192a2bb2ec51b208fd.jpg", "https://greenupload.com/images/2019/01/07/e2ac109e88596b073248.jpg", "https://greenupload.com/images/2019/01/07/eb9141a2d9653a3b6374.jpg" ],
  "intro" : "Gái gọi Cô Giáo Thảo - 2501\n250K/shot\nMBTM Sài gòn\n\nNhà nghỉ60k-80k/h\nLê Hông Phong - Quận 10\nlấy số ở Thiendia\n1989\nXuất xứMiền Tây\nCao160 cm\nDaDa trắng\nMặtMặt xinh dâm\nto hệ bưởi\nEohơi tròn\nTròn căng đét, to\nBímkhông calavat , bót chặt\nServicehôn môi\nhôn vú\nHJ , BJ\nVét máng\nbóp thoải mái\n\n30-40 phút / lần phọt\n11h-23h hàng ngày\nĐánh_giá_chungquá đẹp với giá 250k . nhiệt tình , nhẹ nhàng , vui vẻ , không công nghiệp . đảm bảo rất thích luôn nhé .\nLINK REPORT THAM KHẢO:\n\nhttps://thiendia.com/diendan/thread...en-tay-thac-sy-bu-liem-len-sai-thanh.1209286/"
}, {
  "url" : "https://thiendia.com/diendan/threads/tam-nghi-kieu-my-1304-mot-em-hang-dam-ngon-phuc-vu-tuyet-voi.1208490/",
  "title" : "600K - Quận 5 - [TẠM NGHỈ] Kiều my 1304 - một em hàng dâm ngon , phục vụ tuyệt vời",
  "unixTime" : 1549026000,
  "imgUrls" : [ "https://greenupload.com/images/2019/01/02/2aeb641cbdd05e8e07c1.jpg", "https://greenupload.com/images/2019/01/02/4aacbf58669485cadc85.jpg", "https://greenupload.com/images/2019/01/02/101d3be9e225017b5834.jpg", "https://greenupload.com/images/2019/01/02/961e5ce4852866763f39.jpg", "https://greenupload.com/images/2019/01/02/b3b7db4d0281e1dfb890.jpg", "https://greenupload.com/images/2019/01/02/b5dd93274aeba9b5f0fa.jpg", "https://greenupload.com/images/2019/01/02/b7456fb2b67e55200c6f.jpg", "https://greenupload.com/images/2019/01/02/c0874d7d94b177ef2ea0.jpg", "https://greenupload.com/images/2019/01/02/e5fe5d0184cd67933edc.jpg", "https://greenupload.com/images/2019/01/02/f7e71519ccd52f8b76c4.jpg" ],
  "intro" : "Gái gọi Kiều My - 1304\n600K/shot\nGái gọi Sài Gòn\n\nNhà nghỉ80k-100k/h\nQuận 5\nlấy số ở Thiendia\n1993\nXuất xứMiền Nam\nCao158 cm\nDaDa trắng\nMặtMặt xinh dâm , /TD]\n\nto hệ cam Mỹ\nEophẳng lì\nTròn căng đét\nBímkhông calavat , bót chặt\nServicehôn môi\nhôn vú\nHJ , BJ\nbú bóp thoải mái\nQua đêm\n\ntrên 40 phút / lần phọt\n11h-22h hàng ngày\nĐánh_giá_chungquá đẹp với giá . nhiệt tình , nhẹ nhàng , vui vẻ , không công nghiệp . đảm bảo rất dễ thương luôn nhé .\nLINK REPORT THAM KHẢO:\n...(Link RP)\nhttps://thiendia.com/diendan/thread...oi-thieu-voi-anh-em-ne.1187960/#post-30147305"
}, {
  "url" : "https://thiendia.com/diendan/threads/tam-nghi-minh-anh-6792-ngon-sung-so-dep-dan-don-thang-dan-ong.1208491/",
  "title" : "600K - Quận 5 - [TẠM NGHỈ] Minh anh 6792 - ngon sững sờ , đẹp đần độn Thằng đàn ông",
  "unixTime" : 1549026000,
  "imgUrls" : [ "https://greenupload.com/images/2019/01/02/3c07c6ff1f33fc6da522.jpg", "https://greenupload.com/images/2019/01/02/3ffc2806f1ca12944bdb.jpg", "https://greenupload.com/images/2019/01/02/6df3bd0a64c68798ded7.jpg", "https://greenupload.com/images/2019/01/02/9ff8db0102cde193b8dc.jpg", "https://greenupload.com/images/2019/01/02/38bbe841318dd2d38b9c.jpg", "https://greenupload.com/images/2019/01/02/49b51c4dc58126df7f90.jpg", "https://greenupload.com/images/2019/01/02/370f81f6583abb64e22b.jpg", "https://greenupload.com/images/2019/01/02/581ccae51329f077a938.jpg", "https://greenupload.com/images/2019/01/02/001931e0e82c0b72523d.jpg", "https://greenupload.com/images/2019/01/02/a79ad2620baee8f0b1bf.jpg", "https://greenupload.com/images/2019/01/02/b5b28e4a5786b4d8ed97.jpg", "https://greenupload.com/images/2019/01/02/ba41aeb87774942acd65.jpg", "https://greenupload.com/images/2019/01/02/c8d90b23d2ef31b168fe.jpg", "https://greenupload.com/images/2019/01/02/c9911e69c7a524fb7db4.jpg", "https://greenupload.com/images/2019/01/02/fe819a7843b4a0eaf9a5.jpg" ],
  "intro" : "Gái gọi Minh Anh\n600K/shot\nGái gọi Sài Gòn\n\nNhà nghỉ80k-100k/h\nQuận 5\nlấy số ở Thiendia\n1994\nXuất xứMiền Nam\nCao159 cm\nDaDa trắng\nMặtMặt xinh dâm\nto hệ bưởi\nEophẳng lì\nTròn căng đét\nBímđẹp , múp , bót chặt\nService\nHông môi\nhôn vú\nHJ , BJ\nbú bóp thoải mái\nQua đêm\n\ntrên 40 phút / lần phọt\n11h-22h hàng ngày\nĐánh_giá_chungquá đẹp với giá . nhiệt tình , nhẹ nhàng , vui vẻ , không công nghiệp . đảm bảo rất dễ thương luôn nhé .\nLINK REPORT THAM KHẢO:\n...(Link RP)\n\nhttps://thiendia.com/diendan/thread...nh-cong-ruc-ro-em-that-qua-tuyet-voi.1187993/"
}, {
  "url" : "https://thiendia.com/diendan/threads/vip-massage-ky-anh-xa-dan-dang-cap-cua-su-khac-biet-km-shock-50-cac-hang-ve-ban-co-tin.1212720/",
  "title" : "Massage - Chuẩn - [VIP] Massage Kỳ Anh – Xã Đàn - Đẳng Cấp Của Sự Khác Biệt – KM Shock 50% Các Hạng Vé - Bạn Có Tin ?",
  "unixTime" : 1548919604,
  "imgUrls" : [ "https://greenupload.com/images/2019/01/31/lo-go.jpg", "https://greenupload.com/images/2019/01/31/dn-phong.jpg", "https://greenupload.com/images/2019/01/31/b-xc-vip.jpg", "https://greenupload.com/images/2019/01/31/bo-do-massa-cho-khach.jpg", "https://greenupload.com/images/2019/01/31/giung-da-mui.jpg", "https://greenupload.com/images/2019/01/31/khu-nghi.jpg", "https://greenupload.com/images/2019/01/31/nhan-vien-phong-chung.jpg", "https://greenupload.com/images/2019/01/31/khu-d-do.jpg", "https://greenupload.com/images/2019/01/31/b-xc-chung.jpg", "https://greenupload.com/images/2019/01/31/ban-cha.jpg", "https://greenupload.com/images/2019/01/31/chao-bao-ngu-hai-sam-2.jpg", "https://greenupload.com/images/2019/01/31/chim-cau-tan-hat-sen-long-nhan-3.jpg" ],
  "intro" : "Số Fone Quản Lý : Mr Hóa : 099.777.9988 (Kính Mong Anh Em Hãy Đọc Pass Để Được Áp Dụng Những Khuyến Mại Thật 100% Dành Cho Anh Em Thiên Địa - PASS : BẠN MOVADO )\n\nGiới thiệu qua cơ sở vật chất của Massage Kỳ Anh số 103 ngõ 360 Xã Đàn – Đống Đa – Hà Nội\n\nMassage Kỳ Anh được đầu tư tỉ mỉ với hệ thống trang thiết bị hiện đại bấc nhất Hà Nội ẩn bên trong lối thiết kế mộc mạc tinh tế để mang bạn trở về với thiên nhiên. Tại đây cơ sở được chăm chút công phu từ những chi tiết nhỏ nhất để mang lại cho các bạn có những trải nghiệm thích thú tuyệt vời: kể từ những KTV ( xinh – ngon – ngoan ) được đào tạo bài bản các chiêu trò cùng với tay nghề phục hồi sức khỏe rất very happy cho tới những trang thiết bị phụ trợ chăm sóc sức khỏe cực kì hiện đại và tinh tế.\n\nMassage Kỳ Anh có 3 gói dịch vụ cho các bạn lựa chọn ( Tất Cả Đều Dành Khuyến Mại Sock Tới Tận Óc Cho Các Dân Chơi Nhà Ta )\n\n+ Gói Super Vip giá 950k/ vé giảm sock trong dịp Chào Xuân Kỷ Hợi còn 480k/ vé - Tip Sàn 500k bao gồm các dịch vụ :\n\n- Phòng cao cấp nhất tại Massage Kỳ Anh được sử dụng toàn bộ dịch vụ ưu tiên nhất\n\n- Phòng riêng rộng rãi, hoàn toàn riêng tư, đầy đủ các trang thiết bị cao cấp\n\n- Tùy ý tự chọn 1 trong 5 loại tinh dầu cao cấp nhập khẩu : Oải Hương , Hoa Hồng , Lan Tây , Gỗ Hồng và Romatic\n\n- Bồn tắm Jacuzzi được nghệ nhân đắp hoàn toàn bằng tay theo phong cách Nhật Bản\n\n- Bồn ngâm bằng gỗ sồi ( có thể chọn dược liệu Thuốc Bắc hoặc Tắm Lá Người Dao )\n\n- Phòng xông khô với đá muối Himalaya và phòng không ướt với Xả tươi\n\n- Giường massage bằng đá muối Himalaya đẹp và khỏe đến tê người\n\n- Ghế sofa lớn thoải mái thư giãn – Massage Body 120’ ( HJ, BJ )\n\n- Tùy chọn 1 trong 2 món ăn thập toàn đại bổ : Cháo Bào Ngư Hải Sâm hoặc Gà Ác Tần Bào Ngư Hải Sâm\n\n- Đồ uống tùy chọn theo sở thích : Cà Phê , Nước Ép , Bia ….vv.vvv….\n\n- Gói phục hồi sức khỏe + làm đẹp với các chuyên viên tay nghề cao : Massage Chân, Làm Móng, Đắp Mặt Nạ, Lấy Ráy Tai\n\n+ Gói Vip 750k/ vé giảm sock trong dịp Chào Xuân Kỷ Hợi còn 380k/ vé - Tip Sàn 500k gồm các dịch vụ :\n\n- Phòng hoàn toàn riêng tư với các đầy đủ trang thiết bị cao cấp\n\n- Tùy ý tự chọn 1 trong 3 loại tinh dầu cao cấp nhập khẩu : Lan Tây , Gỗ Hồng và Romatic\n\n- Bồn tắm Jacuzzi được nghệ nhân đắp hoàn toàn bằng tay theo phong cách Nhật Bản\n\n- Bồn ngâm bằng gỗ sồi\n\n- Phòng xông khô với đá muối Himalaya và phòng không ướt với Xả tươi\n\n- Giường massage bằng đá muối Himalaya đẹp và khỏe đến tê người\n\n- Ghế sofa lớn thoải mái thư giãn – Massage Body 120’ ( HJ, BJ )\n\n- Tùy chọn 1 trong 2 món ăn nhẹ : Cháo Thập Toàn Đại Bổ hoặc Chim Câu Tần Hạt Sen Long Nhãn\n\n- Đồ uống tùy chọn theo sở thích : Cà Phê , Nước Ép , Bia ….vv.vvv….\n\n- Gói phục hồi sức khỏe + làm đẹp với các chuyên viên tay nghề cao : Massage Chân, Làm Móng, Đắp Mặt Nạ, Lấy Ráy Tai\n\n+ Gói Tiêu Chuẩn 450k/ vé giảm sock trong dịp Chào Xuân Kỷ Hợi còn 230k /vé - Tip Sàn 400k gồm các dịch vụ :\n\n- Phòng Massage riêng, có phòng tắm, phòng vệ sinh riêng, được trang bị đầy đủ các dụng cụ cơ bản\n\n- Sử dụng thoải mái khu vực tập thể : Xông Khô Đá Muối Himalaya, Xông Ướt, Bồn Ngâm Jacuzzi nóng lạnh, Bàn Chà Lưng , Phòng Chờ Thư Giãn Hiện Đại Cà Tiện Nghi…\n\n- Đồng phục Massage bằng Lụa Tơ Tằm Cao Cấp, Khăn Xông Hơi ..vv..vvv…\n\n- Giường Massage Cao Cấp – Massage Body 60’ ( HJ, BJ )\n\n- Tặng kèm 1 phần Dimsum thập cẩm và đồ uống ( nước suối, trà gừng, trà lipton )\n\n- Có thể nâng cấp chọn các mùi tình dầu cao cấp hơn ( + 50k )\n\n- Có thể nâng cấp thêm gói Massage chân với giá ưu đài ( + 100k )\n\n- Có thể nâng cấp sử dụng thêm các dịch vụ : Đắp Mặt Nạ, Cắt Móng, Lấy Ráy Tai (+ 50k/ dịch vụ )\n\nVới Phương Châm Kinh Doanh Của Kỳ Anh Massage Chỉ Có 1 Chữ Tín Đặt Lên Hàng Đầu. Bản Thân Kỳ Anh Massage Là Ngành Kinh Doanh Dịch Vụ, Cơ Sở Khẳng Định Luôn Là Làm Sao Cố Gắng Để Phục Vụ Hài Lòng Anh Em Nhất Với 95% Sức Lực. Vì Kỳ Anh Massage Hiểu Rằng Chúng Ta Đang Ở Thời Đại Của 4.0 Của Công Nghệ & Thông Tin.\n\nKhẩu Ngữ Của Chúng Tôi : THẾ GIỚI PHẲNG - KỲ ANH ĐI ĐƯỜNG THẲNG\n\nChính Với Phương Châm Đó Chúng Tôi Muốn Mang Tới Sự Lan Tỏa Từ Chính Các Bạn… Sẽ - Đang Và Đã Trải Nghiệm Tại Cơ Sở Của Chúng Tôi . Mỗi Anh Em Là 1 Chuyên Gia PGA Vô Hình Nhưng Cực Kỳ Trân Quý Với Sự Lớn Mạnh Của Sự Khác Biệt Tại Hà Nội.\nĐược Phục Vụ Anh Em Là Vinh Hạnh Của Massage Kỳ Anh !"
}, {
  "url" : "https://thiendia.com/diendan/threads/dang-em-ninja-lead-khong-mac-giap-tan-so-chuyen-nghiep.1212718/",
  "title" : "Dáng em Ninja Lead (không mặc giáp) tan sở - chuyên nghiệp!",
  "unixTime" : 1548918817,
  "imgUrls" : [ "https://uphinhnhanh.com/images/2019/01/31/1963ed70b34937feb.png", "https://uphinhnhanh.com/images/2019/01/31/2499c99ca8f677789.png", "https://uphinhnhanh.com/images/2019/01/31/38638ffe477712a6e.png", "https://uphinhnhanh.com/images/2019/01/31/49d11d884450b3919.png", "https://uphinhnhanh.com/images/2019/01/31/51db72b5255092ebb.png", "https://uphinhnhanh.com/images/2019/01/31/6.png", "https://uphinhnhanh.com/images/2019/01/31/7.png", "https://uphinhnhanh.com/images/2019/01/31/8.png", "https://uphinhnhanh.com/images/2019/01/31/9.png", "https://uphinhnhanh.com/images/2019/01/31/10.png", "https://uphinhnhanh.com/images/2019/01/31/11.png", "https://uphinhnhanh.com/images/2019/01/31/12bac3a96556f9a15a.png" ],
  "intro" : "Trên đường đi làm về thì vô tình gặp được em này cũng tan sở, dáng người thấp, body xôi thịt nhưng thích diện váy ngắn đốn mắt người đi đường!\n\nNhư tiêu đề mình có để \"Chuyên Nghiệp\", em dù mặc váy cực ngắn nhưng cách ngồi, cách em chống chân rất khó để các đấng mày râu xung quanh săm soi em nhé!\n\nLẽ ra mình định không up các ảnh này đâu vì nó có thể sẽ khiến anh em khó chịu trong người nhưng vì đã tác nghiệp rồi thì mình vẫn chia sẻ với các anh em, rằng các em gái dù sexy nhưng vẫn rất cẩn thận kiểu thách đố các anh nhìn ấy!\n\nDáng nàng Ninja khi điều khiển xe\n\nCố gắng soi vào xem có thấy được gì từ nàng không?\n\nNàng kẹp chặt cặp đùi lại như giấu vàng!!!\n\nChuẩn bị dừng đèn đỏ, xem có thấy được gì không nhé\n\nĐây là kết cmn quả!\n\nChuẩn bị gác chân lên để chạy nhé\n\nThú thật với các anh em chứ cái số mình nó vờ lờ lắm, lúc chở con ghệ đi ngoài đường thì thấy các em váy ngắn chạy long nhong lộ cả silip mà đéo làm gì được.\n\nCòn lúc đi 1 mình thì đéo gặp được em nào, mà gặp thì đại loại cứ như vậy đây!"
}, {
  "url" : "https://thiendia.com/diendan/threads/tuyen-massage-cho-vo-co-the-some.1212717/",
  "title" : "PIC - Ho Chi Minh - Tuyển massage cho vợ (có thể some)",
  "unixTime" : 1548917224,
  "imgUrls" : [ "https://greenupload.com/images/2019/01/31/IMG_04301835992d9af759a4.md.jpg", "https://greenupload.com/images/2019/01/31/IMG_041928ab0f3e2b61cf10.md.jpg", "https://greenupload.com/images/2019/01/31/IMG_2566.md.jpg", "https://greenupload.com/images/2019/01/31/IMG_2565.md.jpg", "https://greenupload.com/images/2019/01/31/IMG_0426ed9bd912139bbb7e.md.jpg", "https://greenupload.com/images/2019/01/31/IMG_041567c1bc0a8bc44a0a.md.jpg", "https://greenupload.com/images/2019/01/31/IMG_042289091f5fc9e3d3bb.md.jpg" ],
  "intro" : "Sau vài lần massage yoni và cũng thông tư tưởng thì vợ chồng em mạn phép đang tin tuyển massage cũng như có thể some cùng vợ chồng em trong những dịp sắp tới.\n*** Đôi nét về vợ chồng mình\nMình 28 tuổi còn vợ mình 24 tuổi đều là dân văn phòng, thích trải nghiệm mới trong tình dục và vợ mình khá dâm nhưng cũng rất ngại, thích tình cảm, nhẹ nhàng không quá vồ vập và thiếu tôn trọng phụ nữ nếu có thì vợ mình sẽ tuột hứng và khả năng cho về rất cao.\n***Điều kiện tuyển như sau:\n- Giới tính và độ tuổi: Nam từ 22 - 32 tuổi (vợ mình không muốn chọn người quá lớn tuổi nên các bác lớn hơn sẽ xem xét kỹ hơn)\n- Hình thể: Không quá mập và cũng không quá gầy, chiều cao trên 1m7, khuôn mặt dễ nhìn, sạch sẽ, không mùi cơ thể, không xăm trổ. Khả năng ăn nói tốt, biết cách gợi chuyện để thao3i mái trong cuộc vui.\n- Hàng họ: sạch sẽ, có thể cạo lông vì vợ không thích rậm rạp, dài trên 17cm, to, đầu khấc hồng hào là lợi thế, phải luôn cương trong quá trình làm chứ lúc xìu làm vợ mất hứng thì cũng ...\n- Kỹ năng: Biết massage yoni và massage thư giãn là yêu cầu quan trọng nhất vì vợ mình thích thoải mái và tạo sự gần gũi kích thích hơn còn massage qua loa để được chịch thì đến lúc đó vợ em mất hứng thì chỉ có đi về. Đặc biệt kỹ năng bú liếm phải tốt vì vợ mình rất thích được bú và mơn trớn kích thích cô bé. Nếu thoải mái và làm vợ mình hứng thì có thể some cùng vợ chồng mình nên yêu cầu thêm phải biết cách âu yếm trước, trong và sau quan hệ - thời gian quan hệ phải lâu chứ mới giữa đường đứt gánh thì mất hứng lắm.\n***Ứng tuyển thế nào:\nVì thật sự sau vài lần thì vợ mình mong muốn tuyển kỹ để vui vẻ và thoải mái cho đôi bên nên mình sẽ rõ yêu cầu để sàn lọc cũng như bảo mật thông tin cho cả hai bên.\n- Inbox vào hộp thư thiendia của mình\n- Thông tin inbox gồm: Giới thiệu sơ về bản thân, số zalo thật, kinh nghiệm massage, khả năng, hình ảnh (hàng họ chụp rõ ràng để đánh giá, body rõ mặt) mình tuyệt đối bảo mật những thông tin này cho các bạn nên cứ yên tâm (vì vợ mình mong muốn biết là gặp ai và nhìn họ thế nào trước khi hẹn gặp)\nMình chỉ trao đổi với những ai đáp ứng được yêu cầu trên qua inbox, nếu hợp sẽ add zalo và trao đổi thêm. Sau đó đã chọn ai thì vợ chồng mình sẽ hẹn cafe nói chuyện hợp sẽ tiến tới việc massage và cùng vui vẻ.\nNếu các bạn thấy phù hợp thì hãy inbox có tâm đừng quăng thông tin cụt lủn và không đầy đủ. Mình và vợ rất rõ ràng quan điểm nếu vui vẻ sẵn sàng chia sẻ nhiều hơn dù có thể chưa đáp ứng hết đc yêu cầu của vợ chồng mình (có thể làm bạn để trao đổi nhiều hơn về kinh nghiệm, về cuộc sống, về sở thích...) và cũng mong các bạn sẽ lịch sự, thiện chí và tôn trọng cuộc sống của nhau.\n\n*** Một số hình ảnh của vợ mình"
} ]